Workbook

Sheet Resumen
A1: Resumen del Bloque 3 — GPIO Génesis
A2: Lo que el equipo debe poder responder (checklist de la semana 7)
A4: Concepto (MXN) | B4: =Supuestos!B15 -> 10 | C4: 20 | D4: 100
A5: Variable por copia (IA + comisión) | B5: ='Costos DFS'!$L$31 -> 76.0125 | C5: ='Costos DFS'!$L$31 -> 76.0125 | D5: ='Costos DFS'!$L$31 -> 76.0125
A6: Fijo 12 meses — piloto (lo marcado 'Incluir') | B6: ='Costos DFS'!$K$31 -> 0 | C6: ='Costos DFS'!$K$31 -> 0 | D6: ='Costos DFS'!$K$31 -> 0
A7: Fijo 12 meses — lanzamiento (todo incluido, sin desarrollo) | B7: ='Costos DFS'!$I$31 -> 8942.5 | C7: ='Costos DFS'!$I$31 -> 8942.5 | D7: ='Costos DFS'!$I$31 -> 8942.5
A8: Desarrollo (promedio de 5 ciclos, con horas) | B8: =Desarrollo!$C$18 -> 50082.5 | C8: =Desarrollo!$C$18 -> 50082.5 | D8: =Desarrollo!$C$18 -> 50082.5
A9: COSTO UNITARIO — piloto | B9: =B6/B$4+B5 -> 76.0125 | C9: =C6/C$4+C5 -> 76.0125 | D9: =D6/D$4+D5 -> 76.0125
A10: COSTO UNITARIO — lanzamiento | B10: =B7/B$4+B5 -> 970.2625 | C10: =C7/C$4+C5 -> 523.1375 | D10: =D7/D$4+D5 -> 165.4375
A11: COSTO UNITARIO — lanzamiento + desarrollo | B11: =(B7+B8)/B$4+B5 -> 5978.5125 | C11: =(C7+C8)/C$4+C5 -> 3027.2625 | D11: =(D7+D8)/D$4+D5 -> 666.2625
A12: Precio de venta (provisional) | B12: =Supuestos!$B$3 -> 249 | C12: =Supuestos!$B$3 -> 249 | D12: =Supuestos!$B$3 -> 249
A13: Margen por copia — lanzamiento | B13: =B12-B10 -> -721.2625 | C13: =C12-C10 -> -274.1375 | D13: =D12-D10 -> 83.5625
A14: Margen por copia — lanzamiento + desarrollo | B14: =B12-B11 -> -5729.5125 | C14: =C12-C11 -> -2778.2625 | D14: =D12-D11 -> -417.2625
A16: Respuestas rápidas
A17: Costo unitario a 10 copias (piloto / lanzamiento) | B17: =TEXT(B9,"$#,##0")&" / "&TEXT(B10,"$#,##0")&" MXN" -> $76 / $970 MXN
A18: Costo de IA por jugador, todo el juego (modelo base) | B18: ='Costo IA'!B27 -> 1.3125
A19: Costo de IA por usuario activo al mes — fórmula del curso (30 días) | B19: ='Costo IA'!B30*Supuestos!B17*Supuestos!B14*Supuestos!B2 -> 1.3125
A20: Costo de IA por usuario activo al mes — días de juego reales | B20: ='Costo IA'!B30*Supuestos!B17*Supuestos!B18*Supuestos!B2 -> 0.525
A21: IA como % del ingreso neto por copia | B21: ='Costo IA'!B27/'Costo IA'!B26 -> 0.0075301205
A22: Presupuesto de desarrollo recomendado (promedio) | B22: =Desarrollo!C18 -> 50082.5
A23: De ese presupuesto, dinero real (sin horas) | B23: =Desarrollo!E18 -> 2242.5
A24: Copias para cubrir desarrollo + lanzamiento (equilibrio preliminar; el cálculo formal es del Bloque 4) | B24: =IF(B12-B5>0,(B7+B8)/(B12-B5),"n/a") -> 341.20962
A26: Pendiente del Bloque 4: VPN a 12 meses, punto de equilibrio formal y flujo de caja. Pendiente de ustedes: medir tokens reales, cotizar firma de código y dominio, confirmar horas por ciclo.

Sheet Supuestos
A1: Supuestos y precios — Bloque 3 (GPIO Génesis)
A2: Tipo de cambio (MXN por USD) | B2: 17.5 | C2: Del proyecto (semana 5).
A3: Precio de venta por copia (MXN) | B3: 249 | C3: Del proyecto (semana 5). El precio final se decide en el Bloque 4.
A4: Comisión del canal (Steam) | B4: 0.3 | C4: Del proyecto: 30%. Verificar en la página de Steam antes de entregar.
A5: Tarifa por hora-persona (MXN) | B5: 80 | C5: Ejemplo del curso ($80/h). Es costo de oportunidad: los estudiantes no se pagan en efectivo.
A6: Costos indirectos (% de los directos) | B6: 0.15 | C6: Rango del curso: 10–20%.
A7: Reserva de contingencia | B7: 0.3 | C7: Rango del curso para innovación: 25–40%.
A8: Horas-persona por ciclo de aprendizaje | B8: 80 | C8: SUPUESTO nuestro. 5 ciclos = 400 h ≈ 29 h/semana por persona en 7 semanas: revisar.
A9: Consultas de ayuda por jugador (todo el juego) | B9: 300 | C9: Del proyecto (semana 5).
A10: % de consultas que van a la nube (pistas 1–2 locales) | B10: 0.5 | C10: Crítica del Prompt 6: pistas 1–2 locales, 3–4 nube.
A11: Tokens de entrada por consulta | B11: 3000 | C11: ESTIMADO (instrucciones + JSON del nivel + código + error). Medir con count_tokens.
A12: Tokens de salida por consulta | B12: 400 | C12: ESTIMADO (respuesta de máx. 2 líneas + explicación). Medir con el campo usage.
A13: Factor del tokenizador (sensibilidad) | B13: 1.3 | C13: La página del curso advierte ~30% más tokens en modelos nuevos.
... A15: Copias para el costo unitario (N) | B15: 10 | C15: El checklist pide el costo unitario a 10 unidades.
A16: Modelo de IA base | B16: Claude Haiku 5.5 | C16: Se elige de la lista. Cambia todo el modelo.
A17: Consultas de ayuda por día de uso | B17: 5 | C17: SUPUESTO: sesión de 30–60 min. Medir en el piloto.
A18: Días de juego al mes (realista) | B18: 12 | C18: SUPUESTO. Medir en el piloto.
A20: Precios de la API de Claude (USD por millón de tokens)
A21: Modelo | B21: Entrada | C21: Salida | D21: Fuente
A22: Claude Haiku 4.5 | B22: 1 | C22: 5 | D22: Modelo que usamos en la semana 5.
A23: Claude Haiku 5.5 | B23: 0.1 | C23: 0.5 | D23: El Haiku más nuevo (≤100k tokens de prompt).
A24: Claude Sonnet 5.5 | B24: 2 | C24: 10 | D24: Opción si el copiloto necesitara más calidad.
A26: Fuente: platform.claude.com/docs/en/about-claude/pricing, consultada el 9-oct-2026. La página no muestra fecha de actualización; el curso pide verificar antes de cada cálculo.
A27: Leyenda: azul = dato que ustedes pueden cambiar; amarillo = supuesto nuestro por confirmar; verde = viene de otra hoja; negro = fórmula.

Sheet Inventario
A1: 1. Inventario de costos — todo lo que se nos ocurrió y qué se queda
A3: Actividad | B3: Costo | C3: ¿Indispensable para entregar la propuesta de valor? | D3: Por qué
A4: CREAR: Componentes electrónicos (BOM) y PCB | B4: ver hoja | C4: No | D4: Descartado en la semana 5: el producto es 100% digital.
A5: CREAR: Carcasa, ensamble y pruebas de hardware | B5: ver hoja | C5: No | D5: Descartado: no hay hardware.
A6: CREAR: Horas de programación, arte y diseño de niveles (Godot 4) | B6: ver hoja | C6: Sí | D6: Es el costo dominante. Va en la hoja Desarrollo.
A7: CREAR: Copiloto de IA (API de Claude) y backend (Supabase) | B7: ver hoja | C7: Sí | D7: Es el diferenciador. Va en Costo IA y Costos DFS.
A8: CREAR: Motor Godot 4, assets CC0/MIT/OFL, GitHub | B8: ver hoja | C8: Sí | D8: Se usan gratis.
A9: CREAR: Firma de código de Windows | B9: ver hoja | C9: Sí (para lanzar) | D9: Sin firma Windows avisa al instalar; el piloto va con guía de instalación.
A10: CREAR: Licencias de software de pago (arte, audio) | B10: ver hoja | C10: No | D10: Hay alternativas libres.
A11: DISTRIBUIR: Comisión del canal de venta (Steam / itch.io) | B11: ver hoja | C11: Sí | D11: Es la forma de llegar al jugador.
A12: DISTRIBUIR: Cuota de publicación en Steam | B12: ver hoja | C12: Sí (para lanzar) | D12: Pago único.
A13: DISTRIBUIR: Dominio y página de venta | B13: ver hoja | C13: Sí | D13: Landing en GitHub Pages; dominio opcional.
A14: DISTRIBUIR: Soporte postventa y actualizaciones | B14: ver hoja | C14: Sí | D14: Casi todo es tiempo del equipo.
... A16: DISTRIBUIR: Empaque y envío físico | B16: ver hoja | C16: No | D16: Descarga digital.
A18: Los 'No' no se calculan. Los 'Sí' están en las hojas siguientes.

Sheet Costo IA
A1: 3. El costo que nadie calcula: la IA
A2: Fórmula del curso: costo mensual por usuario = llamadas/día × (tokens entrada + salida) × precio por token × 30
A3: Paso 1 — tokens por consulta (estimados; falta medirlos con count_tokens)
A4: Tokens de entrada | B4: =Supuestos!B11 -> 3000
A5: Tokens de salida | B5: =Supuestos!B12 -> 400
A6: Factor del tokenizador | B6: =Supuestos!B13 -> 1.3
A8: Paso 2 y 3 — costo de una consulta por modelo
A9: Modelo | B9: Entrada USD/M | C9: Salida USD/M | D9: USD por consulta | E9: USD por consulta (tokenizador ×factor) | F9: MXN por consulta
A10: =Supuestos!A22 -> Claude Haiku 4.5 | B10: =Supuestos!B22 -> 1 | C10: =Supuestos!C22 -> 5 | D10: =($B$4*B10+$B$5*C10)/1000000 -> 0.005 | E10: =D10*$B$6 -> 0.0065 | F10: =D10*Supuestos!$B$2 -> 0.0875
A11: =Supuestos!A23 -> Claude Haiku 5.5 | B11: =Supuestos!B23 -> 0.1 | C11: =Supuestos!C23 -> 0.5 | D11: =($B$4*B11+$B$5*C11)/1000000 -> 0.0005 | E11: =D11*$B$6 -> 0.00065 | F11: =D11*Supuestos!$B$2 -> 0.00875
A12: =Supuestos!A24 -> Claude Sonnet 5.5 | B12: =Supuestos!B24 -> 2 | C12: =Supuestos!C24 -> 10 | D12: =($B$4*B12+$B$5*C12)/1000000 -> 0.01 | E12: =D12*$B$6 -> 0.013 | F12: =D12*Supuestos!$B$2 -> 0.175
A14: Costo mensual por usuario activo — fórmula del curso (×30 días), MXN
A15: Consultas por día | B15: Claude Haiku 4.5 | C15: Claude Haiku 5.5 | D15: Claude Sonnet 5.5 | E15: Haiku 5.5 con tokenizador +30%
A16: 3 | B16: =$A16*$D$10*Supuestos!$B$14*Supuestos!$B$2 -> 7.875 | C16: =$A16*$D$11*Supuestos!$B$14*Supuestos!$B$2 -> 0.7875 | D16: =$A16*$D$12*Supuestos!$B$14*Supuestos!$B$2 -> 15.75 | E16: =$A16*$E$11*Supuestos!$B$14*Supuestos!$B$2 -> 1.02375
A17: 10 | B17: =$A17*$D$10*Supuestos!$B$14*Supuestos!$B$2 -> 26.25 | C17: =$A17*$D$11*Supuestos!$B$14*Supuestos!$B$2 -> 2.625 | D17: =$A17*$D$12*Supuestos!$B$14*Supuestos!$B$2 -> 52.5 | E17: =$A17*$E$11*Supuestos!$B$14*Supuestos!$B$2 -> 3.4125
A18: 20 | B18: =$A18*$D$10*Supuestos!$B$14*Supuestos!$B$2 -> 52.5 | C18: =$A18*$D$11*Supuestos!$B$14*Supuestos!$B$2 -> 5.25 | D18: =$A18*$D$12*Supuestos!$B$14*Supuestos!$B$2 -> 105 | E18: =$A18*$E$11*Supuestos!$B$14*Supuestos!$B$2 -> 6.825
A21: Costo por jugador durante todo el juego (MXN) y su peso en el ingreso neto
A22: Escenario | B22: % a la nube | C22: Haiku 4.5 (MXN) | D22: Haiku 5.5 (MXN) | E22: Sonnet 5.5 (MXN) | F22: Haiku 4.5 (% ingreso neto) | G22: Haiku 5.5 (% ingreso neto) | H22: Sonnet 5.5 (% ingreso neto)
A23: Todas las ayudas a la nube | B23: 1 | C23: =Supuestos!$B$9*$B23*$D$10*Supuestos!$B$2 -> 26.25 | D23: =Supuestos!$B$9*$B23*$D$11*Supuestos!$B$2 -> 2.625 | E23: =Supuestos!$B$9*$B23*$D$12*Supuestos!$B$2 -> 52.5 | F23: =C23/$B$26 -> 0.15060241 | G23: =D23/$B$26 -> 0.015060241 | H23: =E23/$B$26 -> 0.30120482
A24: Con pistas 1–2 locales | B24: =Supuestos!B10 -> 0.5 | C24: =Supuestos!$B$9*$B24*$D$10*Supuestos!$B$2 -> 13.125 | D24: =Supuestos!$B$9*$B24*$D$11*Supuestos!$B$2 -> 1.3125 | E24: =Supuestos!$B$9*$B24*$D$12*Supuestos!$B$2 -> 26.25 | F24: =C24/$B$26 -> 0.075301205 | G24: =D24/$B$26 -> 0.0075301205 | H24: =E24/$B$26 -> 0.15060241
A25: Sensibilidad: precio de la API ×10 (todo a la nube) | B25: 1 | C25: =Supuestos!$B$9*$B25*$D$10*Supuestos!$B$2*10 -> 262.5 | D25: =Supuestos!$B$9*$B25*$D$11*Supuestos!$B$2*10 -> 26.25 | E25: =Supuestos!$B$9*$B25*$D$12*Supuestos!$B$2*10 -> 525 | F25: =C25/$B$26 -> 1.5060241 | G25: =D25/$B$26 -> 0.15060241 | H25: =E25/$B$26 -> 3.0120482
A26: Ingreso neto por copia (MXN) = precio × (1 − comisión) | B26: =Supuestos!B3*(1-Supuestos!B4) -> 174.3
A27: Costo de IA por copia con el modelo base y pistas locales (MXN) | B27: =INDEX(C24:E24,1,MATCH(Supuestos!B16,A10:A12,0)) -> 1.3125 | C27: ← este valor alimenta la hoja Costos DFS
A29: Tarea en casa — llamadas/día × tokens × precio × usuarios objetivo (modelo base)
A30: USD por consulta, modelo base | B30: =INDEX(D10:D12,MATCH(Supuestos!B16,A10:A12,0)) -> 0.0005
A31: Usuarios objetivo | B31: MXN/mes (fórmula del curso, 30 días) | C31: MXN/mes (días de juego reales) | D31: MXN/año (días de juego reales) | E31: MXN/mes por usuario (días reales)
A32: 20 | B32: =$A32*Supuestos!$B$17*$B$30*Supuestos!$B$14*Supuestos!$B$2 -> 26.25 | C32: =$A32*Supuestos!$B$17*$B$30*Supuestos!$B$18*Supuestos!$B$2 -> 10.5 | D32: =C32*12 -> 126 | E32: =C32/$A32 -> 0.525
A33: 100 | B33: =$A33*Supuestos!$B$17*$B$30*Supuestos!$B$14*Supuestos!$B$2 -> 131.25 | C33: =$A33*Supuestos!$B$17*$B$30*Supuestos!$B$18*Supuestos!$B$2 -> 52.5 | D33: =C33*12 -> 630 | E33: =C33/$A33 -> 0.525
A34: 1000 | B34: =$A34*Supuestos!$B$17*$B$30*Supuestos!$B$14*Supuestos!$B$2 -> 1312.5 | C34: =$A34*Supuestos!$B$17*$B$30*Supuestos!$B$18*Supuestos!$B$2 -> 525 | D34: =C34*12 -> 6300 | E34: =C34/$A34 -> 0.525
A36: Si se pasa de 'todo en la nube' a 'pistas locales', el costo baja por la fracción que ya no consulta a la API. Los tokens (3,000 / 400) son estimados: la conclusión depende de medirlos.

Sheet Costos DFS
A1: 4. Costos clasificados D / F / S (CREAR y DISTRIBUIR)
A2: D = crea el valor (pocos, no se recortan) · F = flexibles (se negocian o se posponen) · S = establecidos (no los controlamos). Editen las celdas azules; 'Incluir' = 1 cuenta en el piloto, 0 queda fuera (aplica solo al lanzamiento).
A4: # | B4: Concepto | C4: Tipo (D/F/S) | D4: Valor | E4: Moneda (USD/MXN/%) | F4: Frecuencia | G4: Incluir en piloto (1/0) | H4: Valor en MXN | I4: Fijo 12 meses MXN (bruto) | J4: Variable por copia MXN (bruto) | K4: Fijo 12 m MXN (incluido) | L4: Variable/copia MXN (incluido) | M4: Costo unitario a N copias MXN | N4: Fuente / estado | O4: Nota
A5: CREAR
A6: 1 | B6: Copiloto IA: consultas a la API de Claude (modelo base) | C6: D | D6: ='Costo IA'!B27 -> 1.3125 | E6: MXN | F6: Por copia | G6: 1 | H6: =IF(E6="USD",D6*Supuestos!$B$2,IF(E6="%",D6*Supuestos!$B$3,D6)) -> 1.3125 | I6: =IF(F6="Único",H6,IF(F6="Mensual",H6*12,IF(F6="Anual",H6,0))) -> 0 | J6: =IF(OR(F6="Por copia",F6="% precio"),H6,0) -> 1.3125 | K6: =G6*I6 -> 0 | L6: =G6*J6 -> 1.3125 | M6: =K6/Supuestos!$B$15+L6 -> 1.3125 | N6: Hoja Costo IA (estimado) | O6: Costo por jugador durante todo el juego, con pistas locales. Es el diferenciador.
A7: 2 | B7: Supabase plan gratuito (Auth + Postgres + Edge Function) | C7: F | D7: 0 | E7: USD | F7: Mensual | G7: 1 | H7: =IF(E7="USD",D7*Supuestos!$B$2,IF(E7="%",D7*Supuestos!$B$3,D7)) -> 0 | I7: =IF(F7="Único",H7,IF(F7="Mensual",H7*12,IF(F7="Anual",H7,0))) -> 0 | J7: =IF(OR(F7="Por copia",F7="% precio"),H7,0) -> 0 | K7: =G7*I7 -> 0 | L7: =G7*J7 -> 0 | M7: =K7/Supuestos!$B$15+L7 -> 0 | N7: Verificado 9-oct-2026 | O7: Gratis; se pausa tras 1 semana sin actividad. Límites: 500 MB, 50,000 MAU.
A8: 3 | B8: Supabase Pro (si se pasa del plan gratuito) | C8: F | D8: 25 | E8: USD | F8: Mensual | G8: 0 | H8: =IF(E8="USD",D8*Supuestos!$B$2,IF(E8="%",D8*Supuestos!$B$3,D8)) -> 437.5 | I8: =IF(F8="Único",H8,IF(F8="Mensual",H8*12,IF(F8="Anual",H8,0))) -> 5250 | J8: =IF(OR(F8="Por copia",F8="% precio"),H8,0) -> 0 | K8: =G8*I8 -> 0 | L8: =G8*J8 -> 0 | M8: =K8/Supuestos!$B$15+L8 -> 0 | N8: Verificado 9-oct-2026 | O8: Desde $25/mes. Con 10 copias esto solo ya cuesta más que el precio de venta.
A9: 4 | B9: Motor Godot 4 | C9: F | D9: 0 | E9: MXN | F9: Único | G9: 1 | H9: =IF(E9="USD",D9*Supuestos!$B$2,IF(E9="%",D9*Supuestos!$B$3,D9)) -> 0 | I9: =IF(F9="Único",H9,IF(F9="Mensual",H9*12,IF(F9="Anual",H9,0))) -> 0 | J9: =IF(OR(F9="Por copia",F9="% precio"),H9,0) -> 0 | K9: =G9*I9 -> 0 | L9: =G9*J9 -> 0 | M9: =K9/Supuestos!$B$15+L9 -> 0 | N9: Licencia MIT
A10: 5 | B10: Assets CC0 y fuentes OFL | C10: F | D10: 0 | E10: MXN | F10: Único | G10: 1 | H10: =IF(E10="USD",D10*Supuestos!$B$2,IF(E10="%",D10*Supuestos!$B$3,D10)) -> 0 | I10: =IF(F10="Único",H10,IF(F10="Mensual",H10*12,IF(F10="Anual",H10,0))) -> 0 | J10: =IF(OR(F10="Por copia",F10="% precio"),H10,0) -> 0 | K10: =G10*I10 -> 0 | L10: =G10*J10 -> 0 | M10: =K10/Supuestos!$B$15+L10 -> 0 | N10: Licencias CC0/OFL | O10: Anotar la licencia de cada asset.
A11: 6 | B11: Herramientas de arte pixel (software libre) | C11: F | D11: 0 | E11: MXN | F11: Único | G11: 1 | H11: =IF(E11="USD",D11*Supuestos!$B$2,IF(E11="%",D11*Supuestos!$B$3,D11)) -> 0 | I11: =IF(F11="Único",H11,IF(F11="Mensual",H11*12,IF(F11="Anual",H11,0))) -> 0 | J11: =IF(OR(F11="Por copia",F11="% precio"),H11,0) -> 0 | K11: =G11*I11 -> 0 | L11: =G11*J11 -> 0 | M11: =K11/Supuestos!$B$15+L11 -> 0 | N11: Supuesto | O11: Si compran una licencia, cámbienlo aquí.
A12: 7 | B12: Firma de código de Windows (certificado OV) | C12: F | D12: 99 | E12: USD | F12: Anual | G12: 0 | H12: =IF(E12="USD",D12*Supuestos!$B$2,IF(E12="%",D12*Supuestos!$B$3,D12)) -> 1732.5 | I12: =IF(F12="Único",H12,IF(F12="Mensual",H12*12,IF(F12="Anual",H12,0))) -> 1732.5 | J12: =IF(OR(F12="Por copia",F12="% precio"),H12,0) -> 0 | K12: =G12*I12 -> 0 | L12: =G12*J12 -> 0 | M12: =K12/Supuestos!$B$15+L12 -> 0 | N12: ESTIMADO (revendedor, semana 5) | O12: Azure Artifact Signing no acepta organizaciones en México. Piloto sin firma, con guía.
A13: 8 | B13: Repositorio y compilación (GitHub gratuito) | C13: F | D13: 0 | E13: MXN | F13: Único | G13: 1 | H13: =IF(E13="USD",D13*Supuestos!$B$2,IF(E13="%",D13*Supuestos!$B$3,D13)) -> 0 | I13: =IF(F13="Único",H13,IF(F13="Mensual",H13*12,IF(F13="Anual",H13,0))) -> 0 | J13: =IF(OR(F13="Por copia",F13="% precio"),H13,0) -> 0 | K13: =G13*I13 -> 0 | L13: =G13*J13 -> 0 | M13: =K13/Supuestos!$B$15+L13 -> 0 | N13: Supuesto
A14: 9 | B14: Suscripciones de IA para desarrollar (completar) | C14: F | D14: 0 | E14: MXN | F14: Mensual | G14: 1 | H14: =IF(E14="USD",D14*Supuestos!$B$2,IF(E14="%",D14*Supuestos!$B$3,D14)) -> 0 | I14: =IF(F14="Único",H14,IF(F14="Mensual",H14*12,IF(F14="Anual",H14,0))) -> 0 | J14: =IF(OR(F14="Por copia",F14="% precio"),H14,0) -> 0 | K14: =G14*I14 -> 0 | L14: =G14*J14 -> 0 | M14: =K14/Supuestos!$B$15+L14 -> 0 | N14: COMPLETAR | O14: Si pagan alguna, escríbanla aquí.
A15: 10 | B15: Laptops de desarrollo y pruebas (ya las tienen) | C15: F | D15: 0 | E15: MXN | F15: Único | G15: 1 | H15: =IF(E15="USD",D15*Supuestos!$B$2,IF(E15="%",D15*Supuestos!$B$3,D15)) -> 0 | I15: =IF(F15="Único",H15,IF(F15="Mensual",H15*12,IF(F15="Anual",H15,0))) -> 0 | J15: =IF(OR(F15="Por copia",F15="% precio"),H15,0) -> 0 | K15: =G15*I15 -> 0 | L15: =G15*J15 -> 0 | M15: =K15/Supuestos!$B$15+L15 -> 0 | N15: Supuesto | O15: Costo de oportunidad no contado.
B16: Total CREAR | I16: =SUM(I6:I15) -> 6982.5 | J16: =SUM(J6:J15) -> 1.3125 | K16: =SUM(K6:K15) -> 0 | L16: =SUM(L6:L15) -> 1.3125 | M16: =SUM(M6:M15) -> 1.3125
A18: DISTRIBUIR
A19: 1 | B19: Comisión del canal de venta (Steam) | C19: S | D19: =Supuestos!B4 -> 0.3 | E19: % | F19: % precio | G19: 1 | H19: =IF(E19="USD",D19*Supuestos!$B$2,IF(E19="%",D19*Supuestos!$B$3,D19)) -> 74.7 | I19: =IF(F19="Único",H19,IF(F19="Mensual",H19*12,IF(F19="Anual",H19,0))) -> 0 | J19: =IF(OR(F19="Por copia",F19="% precio"),H19,0) -> 74.7 | K19: =G19*I19 -> 0 | L19: =G19*J19 -> 74.7 | M19: =K19/Supuestos!$B$15+L19 -> 74.7 | N19: Del proyecto (verificar) | O19: 30% del precio; por copia.
A20: 2 | B20: Cuota de publicación en Steam | C20: S | D20: 100 | E20: USD | F20: Único | G20: 0 | H20: =IF(E20="USD",D20*Supuestos!$B$2,IF(E20="%",D20*Supuestos!$B$3,D20)) -> 1750 | I20: =IF(F20="Único",H20,IF(F20="Mensual",H20*12,IF(F20="Anual",H20,0))) -> 1750 | J20: =IF(OR(F20="Por copia",F20="% precio"),H20,0) -> 0 | K20: =G20*I20 -> 0 | L20: =G20*J20 -> 0 | M20: =K20/Supuestos!$B$15+L20 -> 0 | N20: Verificado 9-oct-2026 | O20: $100 USD por producto. El piloto va por itch.io (sin cuota).
A21: 3 | B21: Dominio gpiogenesis.com | C21: F | D21: 12 | E21: USD | F21: Anual | G21: 0 | H21: =IF(E21="USD",D21*Supuestos!$B$2,IF(E21="%",D21*Supuestos!$B$3,D21)) -> 210 | I21: =IF(F21="Único",H21,IF(F21="Mensual",H21*12,IF(F21="Anual",H21,0))) -> 210 | J21: =IF(OR(F21="Por copia",F21="% precio"),H21,0) -> 0 | K21: =G21*I21 -> 0 | L21: =G21*J21 -> 0 | M21: =K21/Supuestos!$B$15+L21 -> 0 | N21: ESTIMADO (no se cotizó) | O21: Sin registro al 23-sep-2026. Opcional en el piloto.
A22: 4 | B22: Página de venta en GitHub Pages | C22: F | D22: 0 | E22: MXN | F22: Único | G22: 1 | H22: =IF(E22="USD",D22*Supuestos!$B$2,IF(E22="%",D22*Supuestos!$B$3,D22)) -> 0 | I22: =IF(F22="Único",H22,IF(F22="Mensual",H22*12,IF(F22="Anual",H22,0))) -> 0 | J22: =IF(OR(F22="Por copia",F22="% precio"),H22,0) -> 0 | K22: =G22*I22 -> 0 | L22: =G22*J22 -> 0 | M22: =K22/Supuestos!$B$15+L22 -> 0 | N22: Supuesto
A23: 5 | B23: Alojamiento de descargas (itch.io / GitHub Releases) | C23: F | D23: 0 | E23: MXN | F23: Único | G23: 1 | H23: =IF(E23="USD",D23*Supuestos!$B$2,IF(E23="%",D23*Supuestos!$B$3,D23)) -> 0 | I23: =IF(F23="Único",H23,IF(F23="Mensual",H23*12,IF(F23="Anual",H23,0))) -> 0 | J23: =IF(OR(F23="Por copia",F23="% precio"),H23,0) -> 0 | K23: =G23*I23 -> 0 | L23: =G23*J23 -> 0 | M23: =K23/Supuestos!$B$15+L23 -> 0 | N23: Supuesto
A24: 6 | B24: Marketing digital orgánico (GitHub + YouTube) | C24: F | D24: 0 | E24: MXN | F24: Mensual | G24: 1 | H24: =IF(E24="USD",D24*Supuestos!$B$2,IF(E24="%",D24*Supuestos!$B$3,D24)) -> 0 | I24: =IF(F24="Único",H24,IF(F24="Mensual",H24*12,IF(F24="Anual",H24,0))) -> 0 | J24: =IF(OR(F24="Por copia",F24="% precio"),H24,0) -> 0 | K24: =G24*I24 -> 0 | L24: =G24*J24 -> 0 | M24: =K24/Supuestos!$B$15+L24 -> 0 | N24: Supuesto | O24: Cuesta horas, no efectivo.
A25: 7 | B25: Soporte postventa (correo/Discord) | C25: F | D25: 0 | E25: MXN | F25: Mensual | G25: 1 | H25: =IF(E25="USD",D25*Supuestos!$B$2,IF(E25="%",D25*Supuestos!$B$3,D25)) -> 0 | I25: =IF(F25="Único",H25,IF(F25="Mensual",H25*12,IF(F25="Anual",H25,0))) -> 0 | J25: =IF(OR(F25="Por copia",F25="% precio"),H25,0) -> 0 | K25: =G25*I25 -> 0 | L25: =G25*J25 -> 0 | M25: =K25/Supuestos!$B$15+L25 -> 0 | N25: Supuesto | O25: Cuesta horas, no efectivo.
A26: 8 | B26: Actualizaciones y parches (equivalente al OTA) | C26: S | D26: 0 | E26: MXN | F26: Único | G26: 1 | H26: =IF(E26="USD",D26*Supuestos!$B$2,IF(E26="%",D26*Supuestos!$B$3,D26)) -> 0 | I26: =IF(F26="Único",H26,IF(F26="Mensual",H26*12,IF(F26="Anual",H26,0))) -> 0 | J26: =IF(OR(F26="Por copia",F26="% precio"),H26,0) -> 0 | K26: =G26*I26 -> 0 | L26: =G26*J26 -> 0 | M26: =K26/Supuestos!$B$15+L26 -> 0 | N26: Supuesto | O26: Steam e itch.io las distribuyen sin cargo.
A27: 9 | B27: Pasarela de pago propia (solo si venden fuera de Steam/itch) | C27: F | D27: 0 | E27: MXN | F27: Por copia | G27: 0 | H27: =IF(E27="USD",D27*Supuestos!$B$2,IF(E27="%",D27*Supuestos!$B$3,D27)) -> 0 | I27: =IF(F27="Único",H27,IF(F27="Mensual",H27*12,IF(F27="Anual",H27,0))) -> 0 | J27: =IF(OR(F27="Por copia",F27="% precio"),H27,0) -> 0 | K27: =G27*I27 -> 0 | L27: =G27*J27 -> 0 | M27: =K27/Supuestos!$B$15+L27 -> 0 | N27: No cotizado | O27: Hay que cotizarla si se vende directo.
A28: 10 | B28: Impuestos y contador (ISR/IVA) | C28: S | D28: 0 | E28: MXN | F28: Anual | G28: 0 | H28: =IF(E28="USD",D28*Supuestos!$B$2,IF(E28="%",D28*Supuestos!$B$3,D28)) -> 0 | I28: =IF(F28="Único",H28,IF(F28="Mensual",H28*12,IF(F28="Anual",H28,0))) -> 0 | J28: =IF(OR(F28="Por copia",F28="% precio"),H28,0) -> 0 | K28: =G28*I28 -> 0 | L28: =G28*J28 -> 0 | M28: =K28/Supuestos!$B$15+L28 -> 0 | N28: NO CALCULADO | O28: Consultar con un contador antes de vender.
B29: Total DISTRIBUIR | I29: =SUM(I19:I28) -> 1960 | J29: =SUM(J19:J28) -> 74.7 | K29: =SUM(K19:K28) -> 0 | L29: =SUM(L19:L28) -> 74.7 | M29: =SUM(M19:M28) -> 74.7
B31: TOTAL CREAR + DISTRIBUIR | I31: =I16+I29 -> 8942.5 | J31: =J16+J29 -> 76.0125 | K31: =K16+K29 -> 0 | L31: =L16+L29 -> 76.0125 | M31: =M16+M29 -> 76.0125
B33: Clasificación (conteo)
B34: D | C34: =COUNTIF(C6:C15,"D")+COUNTIF(C19:C28,"D") -> 1
B35: F | C35: =COUNTIF(C6:C15,"F")+COUNTIF(C19:C28,"F") -> 15
B36: S | C36: =COUNTIF(C6:C15,"S")+COUNTIF(C19:C28,"S") -> 4
B38: Regla del curso: si el modelo no cierra, reducir primero los F, aceptar los S, y si hay que tocar un D la propuesta de valor se replantea.
B39: Las horas-persona de desarrollo NO están aquí: van en la hoja Desarrollo y se suman en Resumen.

Sheet Desarrollo
A1: 5. Costos de desarrollo — ciclos de aprendizaje
A2: Fórmula del curso: directos fijos + directos variables + indirectos (10–20%) + reserva de contingencia (25–40%).
A3: Concepto (por ciclo) | B3: MXN | C3: Nota
A4: Horas-persona por ciclo | B4: =Supuestos!B8 -> 80 | C4: Supuesto nuestro (nivel 1 + menú se estimó en ~87 h en la semana 6).
A5: Tarifa por hora (MXN) | B5: =Supuestos!B5 -> 80 | C5: Ejemplo del curso.
A6: Mano de obra | B6: =B4*B5 -> 6400
A7: Directos variables (API en pruebas, incentivos de playtest) | B7: 300 | C7: ESTIMADO.
A8: Directos fijos (licencias por ciclo) | B8: 0 | C8: Todo el software es gratuito.
A9: Costos directos | B9: =B6+B7+B8 -> 6700
A10: Indirectos | B10: =B9*Supuestos!B6 -> 1005
A11: Subtotal | B11: =B9+B10 -> 7705
A12: Reserva de contingencia | B12: =B11*Supuestos!B7 -> 2311.5
A13: COSTO POR CICLO | B13: =B11+B12 -> 10016.5
A16: Escenario | B16: Ciclos | C16: Total MXN (con horas) | D16: Total USD | E16: Solo efectivo MXN (sin horas) | F16: Horas-persona
A17: Mínimo | B17: 3 | C17: =B17*$B$13 -> 30049.5 | D17: =C17/Supuestos!$B$2 -> 1717.1143 | E17: =B17*($B$7+$B$8)*(1+Supuestos!$B$6)*(1+Supuestos!$B$7) -> 1345.5 | F17: =B17*$B$4 -> 240
A18: Promedio (presupuesto recomendado) | B18: 5 | C18: =B18*$B$13 -> 50082.5 | D18: =C18/Supuestos!$B$2 -> 2861.8571 | E18: =B18*($B$7+$B$8)*(1+Supuestos!$B$6)*(1+Supuestos!$B$7) -> 2242.5 | F18: =B18*$B$4 -> 400
A19: Máximo | B19: 8 | C19: =B19*$B$13 -> 80132 | D19: =C19/Supuestos!$B$2 -> 4578.9714 | E19: =B19*($B$7+$B$8)*(1+Supuestos!$B$6)*(1+Supuestos!$B$7) -> 3588 | F19: =B19*$B$4 -> 640
A21: El curso recomienda presentar el escenario promedio. El dinero real que sale del bolsillo es la columna 'Solo efectivo'; las horas son costo de oportunidad.
