Workbook

Sheet Resumen
A1: Resumen — viabilidad económica de GPIO Génesis (semana 7)
A2: Checklist de salida de la semana 7. Todo se calcula en las otras hojas; cambien los supuestos (azul/amarillo) y esto se actualiza.
A4: Pregunta del checklist | B4: MVP (5 niveles) | C4: 3 bloques (22 niveles)
A5: Costo unitario a 10 copias (todo incluido) | B5: ='Costo unitario'!B12 -> 6030.042 | C5: ='Costo unitario'!D12 -> 12606.342
A6: Costo unitario a 100 copias (todo incluido) | B6: ='Costo unitario'!C12 -> 671.0082 | C6: ='Costo unitario'!E12 -> 1333.5162
A7: Costo variable por copia (IA + comisión) | B7: ='Costo unitario'!B13 -> 75.56 | C7: ='Costo unitario'!D13 -> 80.98
A8: Modelo de ingresos | B8: Juego $249 (pago único en Steam) + Copiloto Pro $49/mes opcional
A9: Costo de IA al mes por usuario activo — plan base (5 consultas/día × 30 días) | B9: =5*Supuestos!$B$16*Supuestos!$B$17*Supuestos!$B$18*Supuestos!$B$5 -> 1.3125
A10: Costo de IA al mes por suscriptor Pro (10 consultas/día × 30 días) | B10: =Supuestos!$B$40 -> 2.625
A11: Equilibrio del año 1, contando horas (copias) | B11: =Equilibrio!B12 -> 322 | C11: =Equilibrio!C12 -> 697
A12: Equilibrio del año 1, solo efectivo (copias) | B12: =Equilibrio!B13 -> 49 | C12: =Equilibrio!C13 -> 50
A14: VPN a 12 meses (15% anual) | B14: MVP | C14: 3 bloques
A15: VPN contando horas — escenario pesimista | B15: ='Flujo 12 meses'!C19 -> -33289.101 | C15: ='Flujo 12 meses'!C76 -> -99737.576
A16: VPN contando horas — escenario base | B16: ='Flujo 12 meses'!C38 -> 9829.4277 | C16: ='Flujo 12 meses'!C95 -> -57892.172
A17: VPN contando horas — escenario optimista | B17: ='Flujo 12 meses'!C57 -> 130561.31 | C17: ='Flujo 12 meses'!C114 -> 59274.959
A18: VPN solo efectivo — escenario pesimista | B18: ='Flujo 12 meses'!G19 -> 17301.699 | C18: ='Flujo 12 meses'!G76 -> 16513.624
A19: VPN solo efectivo — escenario base | B19: ='Flujo 12 meses'!G38 -> 60420.228 | C19: ='Flujo 12 meses'!G95 -> 58359.028
A20: VPN solo efectivo — escenario optimista | B20: ='Flujo 12 meses'!G57 -> 181152.11 | C20: ='Flujo 12 meses'!G114 -> 175526.16
A21: Mes en que el acumulado (contando horas) se vuelve positivo — pesimista | B21: ='Flujo 12 meses'!C20 -> no en 12 meses | C21: ='Flujo 12 meses'!C77 -> no en 12 meses
A22: Mes en que el acumulado (contando horas) se vuelve positivo — base | B22: ='Flujo 12 meses'!C39 -> 9 | C22: ='Flujo 12 meses'!C96 -> no en 12 meses
A23: Mes en que el acumulado (contando horas) se vuelve positivo — optimista | B23: ='Flujo 12 meses'!C58 -> 2 | C23: ='Flujo 12 meses'!C115 -> 7
A25: ¿VPN positivo con el escenario base? | B25: =IF('Flujo 12 meses'!C38>0,"Sí","No") -> Sí | C25: =IF('Flujo 12 meses'!C95>0,"Sí","No") -> No
A26: Multiplicador del precio de la API usado | B26: =Supuestos!$B$18 -> 1

Sheet Supuestos
A1: Supuestos del modelo financiero — GPIO Génesis (semana 7, Bloque 4)
A2: Azul = dato editable · amarillo = supuesto de Claude por confirmar · verde = viene de los Excel del Bloque 3 (costos-gpio-genesis-semana7.xlsx y alcance-niveles-costos-gpio-genesis.xlsx).
A4: Concepto | B4: Valor | C4: Unidad | D4: Fuente / nota
A5: Tipo de cambio | B5: 17.5 | C5: MXN/USD | D5: Del proyecto (semana 5).
A6: Tipo de cambio | B6: 20.5 | C6: MXN/EUR | D6: ESTIMADO, solo para convertir el precio de Wokwi.
A7: Precio del juego (capa 1, pago único) | B7: 249 | C7: MXN | D7: Del proyecto (semanas 4–5). Rango de disposición de pago 100–400 MXN.
A8: Comisión de Steam | B8: 0.3 | C8: % | D8: 30% hasta US$10 M de ventas (reparto escalonado de Valve, 2018).
A9: Precio de Copiloto Pro (capa 2, suscripción) | B9: 49 | C9: MXN/mes | D9: Propuesta de Claude: debajo de Wokwi Hobby y de CodeCombat (hoja Benchmark).
A10: Comisión de la pasarela (Stripe México) — % | B10: 0.036 | C10: % | D10: stripe.com/mx/pricing, consultado 22-oct-2026. La suscripción se cobra en la página web, no en Steam.
A11: Comisión de la pasarela — fija | B11: 3 | C11: MXN/cobro | D11: stripe.com/mx/pricing. Las comisiones no incluyen IVA.
A12: IVA sobre la comisión de la pasarela | B12: 0.16 | C12: % | D12: IVA general en México.
A13: Compradores que se suscriben a Pro | B13: 0.1 | C13: % | D13: SUPUESTO. En la semana 4, 3 de 4 entrevistados ven esto como 'comprar un juego': validar en el piloto.
A14: Bajas mensuales de suscriptores | B14: 0.35 | C14: %/mes | D14: SUPUESTO alto: el jugador deja Pro cuando termina el juego o el semestre.
A15: Consultas a la nube por día — suscriptor Pro | B15: 10 | C15: consultas/día | D15: SUPUESTO (el plan base tiene cuota de 10/h y pistas 1–2 locales).
A16: Días por mes (fórmula del curso) | B16: 30 | C16: días | D16: Cota superior: supone uso diario.
... A34: Copias en el año 1 — escenario optimista | B34: 1100 | C34: copias | D34: Igual al SOM completo.
A36: Calculados
A37: Tasa mensual equivalente | B37: =(1+Supuestos!$B$29)^(1/12)-1 -> 0.011714917
A38: Ingreso neto por copia (precio − comisión) | B38: =Supuestos!$B$7*(1-Supuestos!$B$8) -> 174.3
A39: Comisión de pasarela por cobro de Pro, con IVA | B39: =(Supuestos!$B$9*Supuestos!$B$10+Supuestos!$B$11)*(1+Supuestos!$B$12) -> 5.52624
A40: IA por suscriptor Pro al mes (fórmula del curso) | B40: =Supuestos!$B$15*Supuestos!$B$16*Supuestos!$B$17*Supuestos!$B$18*Supuestos!$B$5 -> 2.625
A41: Lanzamiento año 1 sin Supabase (Steam + dominio + firma) | B41: =(Supuestos!$B$25+Supuestos!$B$26+Supuestos!$B$27)*Supuestos!$B$5 -> 3692.5
A42: Supabase Pro al mes | B42: =Supuestos!$B$28*Supuestos!$B$5 -> 437.5
A43: Vida media de un suscriptor (1 / bajas) | B43: =1/Supuestos!$B$14 -> 2.8571429
A45: Reparto de las ventas del año 1 por mes (suma 100%) | D45: SUPUESTO: pico de lanzamiento, cola, y repunte en el mes 6 (inicio de semestre).
A46: Mes 1 | B46: 0.2
A47: Mes 2 | B47: 0.12
A48: Mes 3 | B48: 0.08
A49: Mes 4 | B49: 0.06
A50: Mes 5 | B50: 0.06
A51: Mes 6 | B51: 0.1
A52: Mes 7 | B52: 0.08
A53: Mes 8 | B53: 0.06
A54: Mes 9 | B54: 0.05
A55: Mes 10 | B55: 0.05
A56: Mes 11 | B56: 0.06
A57: Mes 12 | B57: 0.08
A58: Suma | B58: =SUM(B46:B57) -> 1

Sheet Benchmark
A1: Bloque 2 — Benchmarking de ofertas parecidas y modelos de ingreso
A3: Oferta | B3: Qué es | C3: Modelo de ingreso | D3: Precio | E3: Moneda | F3: MXN | G3: Fricción para nuestro segmento | H3: Fuente (consultada 22-oct-2026)
A4: SHENZHEN I/O (Zachtronics) | B4: Juego de puzles: circuitos con microcontroladores y ensamblador ficticio | C4: Pago único | D4: 14.99 | E4: USD | F4: =D4*Supuestos!$B$5 -> 262.325 | G4: Lenguaje inventado: no se transfiere a un microcontrolador real; en inglés | H4: zachtronics.itch.io/shenzhen-io
A5: Turing Complete (LevelHead) | B5: Juego: construir una computadora desde compuertas lógicas | C5: Pago único | D5: 19.99 | E5: USD | F5: =D5*Supuestos!$B$5 -> 349.825 | G5: Enseña arquitectura, no programación de periféricos; en inglés | H5: steambase.io (precio de Steam)
A6: Wokwi Hobby | B6: Simulador web de Arduino / ESP32 / Raspberry Pi Pico | C6: Freemium + suscripción | D6: 5.6 | E6: EUR/mes | F6: =D6*Supuestos!$B$6 -> 114.8 | G6: Es una herramienta, no un juego: no guía ni motiva; el plan gratis ya simula | H6: wokwi.com/pricing (facturación anual)
A7: CodeCombat (semana 4) | B7: RPG para aprender a programar (incluye C++) | C7: Freemium + suscripción | D7: 9.99 | E7: USD/mes | F7: =D7*Supuestos!$B$5 -> 174.825 | G7: Abstracto, sin simulación de hardware; 'otra plataforma de cursos' | H7: Semana 4 (mapa competitivo)
A8: TIS-100 (semana 4) | B8: Puzles de ensamblador en una arquitectura ficticia | C8: Pago único | D8: 119 | E8: MXN | F8: =D8*1 -> 119 | G8: Bajo nivel no transferible a C/C++ | H8: Semana 4 (mapa competitivo)
A10: Lectura: los juegos de programación se venden por pago único entre ~$120 y ~$350 MXN; las herramientas y plataformas cobran suscripción de ~$115–175 MXN/mes.
A11: Techo del juego (value-based) = el juego más caro de la lista; techo de Pro = la suscripción más barata de la lista.
A13: Los 5 modelos de ingreso de IDEO aplicados a GPIO Génesis
A14: Modelo | B14: Cómo sería en GPIO Génesis | C14: Reto de diseño (IDEO) | D14: ¿Lo usamos? | G14: Por qué
A15: Pago por evento | B15: Comprar el juego una vez en Steam ($249) | C15: Que el valor se sienta completo en una sola compra | D15: Sí — capa 1 | G15: Es lo que dijeron los entrevistados (semana 4) y lo que hacen Shenzhen I/O y Turing Complete.
A16: Suscripción | B16: Copiloto Pro: más consultas en la nube, revisión de código y reporte para portafolio | C16: Dar valor nuevo cada mes para que no se cancele | D16: Sí — capa 2 (opcional) | G16: Es la versión digital de 'hardware + suscripción' del curso. El juego funciona completo sin ella.
A17: Publicidad | B17: Anuncios dentro del juego o patrocinios de fabricantes de placas | C17: Que el anuncio no rompa la experiencia | D17: No | G17: Arruina un juego de pago; un patrocinio de fabricante podría servir más adelante.
A18: Freemium | B18: Nivel 1 gratis como demo | C18: Que lo gratis enganche sin regalar todo | D18: Solo como demo | G18: La demo de Steam sirve de marketing, no como fuente de ingreso.
A19: Pago por uso | B19: Cobrar por consulta al copiloto | C19: Que el usuario entienda cuánto gasta | D19: No | G19: Cobrar cada pregunta castiga justo al que más necesita ayuda.

Sheet Costo unitario
A1: Paso 1 — Costo unitario real (por copia)
A2: En un producto digital no hay BOM ni manufactura por pieza: la 'manufactura' es el desarrollo, que se reparte entre las copias. El desarrollo ya trae indirectos (15%) y contingencia (30%), por eso no se vuelven a sumar.
A4: Concepto (MXN por copia) | B4: MVP · 10 copias | C4: MVP · 100 copias | D4: 3 bloques · 10 copias | E4: 3 bloques · 100 copias
A5: Unidades | B5: 10 | C5: 100 | D5: 10 | E5: 100
A6: BOM / hardware | B6: =0 -> 0 | C6: =0 -> 0 | D6: =0 -> 0 | E6: =0 -> 0
A7: Desarrollo repartido ('manufactura') | B7: =Supuestos!$B$21/B5 -> 5059.656 | C7: =Supuestos!$B$21/C5 -> 505.9656 | D7: =Supuestos!$B$22/D5 -> 11628.116 | E7: =Supuestos!$B$22/E5 -> 1162.8116
A8: Lanzamiento repartido (Steam, dominio, firma) | B8: =(Supuestos!$B$41+Supuestos!$B$23)/B5 -> 369.826 | C8: =(Supuestos!$B$41+Supuestos!$B$23)/C5 -> 36.9826 | D8: =(Supuestos!$B$41+Supuestos!$B$24)/D5 -> 372.246 | E8: =(Supuestos!$B$41+Supuestos!$B$24)/E5 -> 37.2246
A9: Nube repartida (Supabase Pro 12 meses) | B9: =Supuestos!$B$42*12/B5 -> 525 | C9: =Supuestos!$B$42*12/C5 -> 52.5 | D9: =Supuestos!$B$42*12/D5 -> 525 | E9: =Supuestos!$B$42*12/E5 -> 52.5
A10: IA del copiloto por jugador | B10: =Supuestos!$B$19*Supuestos!$B$18 -> 0.86 | C10: =Supuestos!$B$19*Supuestos!$B$18 -> 0.86 | D10: =Supuestos!$B$20*Supuestos!$B$18 -> 6.28 | E10: =Supuestos!$B$20*Supuestos!$B$18 -> 6.28
A11: Comisión de Steam (30% del precio) | B11: =Supuestos!$B$7*Supuestos!$B$8 -> 74.7 | C11: =Supuestos!$B$7*Supuestos!$B$8 -> 74.7 | D11: =Supuestos!$B$7*Supuestos!$B$8 -> 74.7 | E11: =Supuestos!$B$7*Supuestos!$B$8 -> 74.7
A12: COSTO UNITARIO TOTAL | B12: =SUM(B6:B11) -> 6030.042 | C12: =SUM(C6:C11) -> 671.0082 | D12: =SUM(D6:D11) -> 12606.342 | E12: =SUM(E6:E11) -> 1333.5162
A13: de eso, variable (IA + comisión) | B13: =B10+B11 -> 75.56 | C13: =C10+C11 -> 75.56 | D13: =D10+D11 -> 80.98 | E13: =E10+E11 -> 80.98
A14: de eso, dinero real (sin horas de desarrollo) | B14: =B12-B7 -> 970.386 | C14: =C12-C7 -> 165.0426 | D14: =D12-D7 -> 978.226 | E14: =E12-E7 -> 170.7046
A15: Precio actual | B15: =Supuestos!$B$7 -> 249 | C15: =Supuestos!$B$7 -> 249 | D15: =Supuestos!$B$7 -> 249 | E15: =Supuestos!$B$7 -> 249
A16: Margen por copia | B16: =B15-B12 -> -5781.042 | C16: =C15-C12 -> -422.0082 | D16: =D15-D12 -> -12357.342 | E16: =E15-E12 -> -1084.5162
A18: Lectura: a 10 copias el desarrollo pesa miles de pesos por copia; el costo de verdad variable (IA + comisión) es de ~$76–81 por copia. El precio no se puede fijar con el costo unitario a 10 copias: hay que mirar el volumen (Paso 3).

Sheet Precio
A1: Paso 2 — Precio de venta: piso (cost-plus) y techo (value-based)
A3: Capa 1 — juego (MXN) | B3: MVP | C3: 3 bloques | D3: Nota
A4: Copias para repartir el costo fijo (escenario base) | B4: =Supuestos!$B$33 -> 400 | C4: =Supuestos!$B$33 -> 400
A5: Costo por copia sin comisión (fijo/copias + IA) | B5: =(Supuestos!$B$21+Supuestos!$B$41+Supuestos!$B$23+Supuestos!$B$42*12)/B4+Supuestos!$B$19*Supuestos!$B$18 -> 149.72205 | C5: =(Supuestos!$B$22+Supuestos!$B$41+Supuestos!$B$24+Supuestos!$B$42*12)/C4+Supuestos!$B$20*Supuestos!$B$18 -> 319.41405
A6: Lo que debemos recibir con margen de 40% | B6: =B5*(1+Supuestos!$B$30) -> 209.61087 | C6: =C5*(1+Supuestos!$B$30) -> 447.17967
A7: PISO cost-plus: precio en tienda (ya con el 30% de Steam) | B7: =B6/(1-Supuestos!$B$8) -> 299.4441 | C7: =C6/(1-Supuestos!$B$8) -> 638.8281 | D7: precio = costo × 1.4 ÷ (1 − 0.30)
A8: TECHO value-based (Turing Complete, el más caro del benchmark) | B8: =Benchmark!$F$5 -> 349.825 | C8: =Benchmark!$F$5 -> 349.825 | D8: La entrevista de la semana 4 dio 100–400 MXN; Turing Complete ≈ $350.
A9: Precio recomendado | B9: =Supuestos!$B$7 -> 249 | C9: =Supuestos!$B$7 -> 249 | D9: Se queda en $249: entra en 199–299 (semana 4) y queda entre Shenzhen I/O y Turing Complete.
A10: ¿El recomendado cubre el piso? | B10: =IF(B9>=B7,"Cubre el piso cost-plus",IF(B9>=B5/(1-Supuestos!$B$8),"Cubre costos, no el 40%","No cubre costos")) -> Cubre costos, no el 40% | C10: =IF(C9>=C7,"Cubre el piso cost-plus",IF(C9>=C5/(1-Supuestos!$B$8),"Cubre costos, no el 40%","No cubre costos")) -> No cubre costos
A12: Capa 2 — Copiloto Pro (MXN/mes) | B12: Valor | D12: Nota
A13: Costo por suscriptor al mes (IA + pasarela con IVA) | B13: =Supuestos!$B$40+Supuestos!$B$39 -> 8.15124
A14: PISO cost-plus (×1.4) | B14: =B13*(1+Supuestos!$B$30) -> 11.411736 | D14: La IA cuesta tan poco con Haiku 5.5 que el piso queda en pocos pesos: el piso no decide el precio.
A15: TECHO value-based (Wokwi Hobby, la suscripción más barata) | B15: =Benchmark!$F$6 -> 114.8
A16: Precio recomendado | B16: =Supuestos!$B$9 -> 49 | D16: Muy por debajo del techo: el reto no es el precio sino que alguien quiera pagar cada mes (IDEO: dar valor nuevo cada mes).
A17: Margen por suscriptor al mes | B17: =B16-B13 -> 40.84876
A18: Margen esperado de Pro por cada copia vendida (conversión × vida media × margen) | B18: =Supuestos!$B$13*Supuestos!$B$43*B17 -> 11.671074

Sheet Flujo 12 meses
A1: Paso 4 — Flujo de caja a 12 meses (MXN) por alcance y escenario de ventas
A2: Mes 0 = inversión: desarrollo contando horas + cuota de Steam, dominio y firma. 'Efectivo' = lo mismo pero sin las horas (el dinero que de verdad sale del bolsillo). VPN con la tasa anual del curso convertida a mensual.
A4: ="MVP · escenario pesimista — copias en el año 1: "&TEXT(Supuestos!$B$32,"#,##0") -> MVP · escenario pesimista — copias en el año 1: 150
A5: Mes | B5: Copias vendidas | C5: Ventas del juego | D5: Comisión Steam | E5: IA de jugadores | F5: Suscriptores Pro (fin de mes) | G5: Ventas de Pro | H5: Comisión pasarela | I5: IA de Pro | J5: Supabase Pro | K5: Inversión | L5: FLUJO NETO | M5: Acumulado | N5: Flujo solo efectivo | O5: Acumulado efectivo
A6: 0 | B6: =0 -> 0 | C6: =B6*Supuestos!$B$7 -> 0 | D6: =-C6*Supuestos!$B$8 -> 0 | E6: =-B6*Supuestos!$B$19*Supuestos!$B$18 -> 0 | F6: =0 -> 0 | G6: =F6*Supuestos!$B$9 -> 0 | H6: =-F6*Supuestos!$B$39 -> 0 | I6: =-F6*Supuestos!$B$40 -> 0 | J6: =0 -> 0 | K6: =-(Supuestos!$B$21+Supuestos!$B$41) -> -54289.06 | L6: =C6+D6+E6+G6+H6+I6+J6+K6 -> -54289.06 | M6: =L6 -> -54289.06 | N6: =L6-K6-(Supuestos!$B$41+Supuestos!$B$23) -> -3698.26 | O6: =N6 -> -3698.26
A7: 1 | B7: =Supuestos!$B$32*Supuestos!$B$46 -> 30 | C7: =B7*Supuestos!$B$7 -> 7470 | D7: =-C7*Supuestos!$B$8 -> -2241 | E7: =-B7*Supuestos!$B$19*Supuestos!$B$18 -> -25.8 | F7: =F6*(1-Supuestos!$B$14)+B7*Supuestos!$B$13 -> 3 | G7: =F7*Supuestos!$B$9 -> 147 | H7: =-F7*Supuestos!$B$39 -> -16.57872 | I7: =-F7*Supuestos!$B$40 -> -7.875 | J7: =-Supuestos!$B$42 -> -437.5 | K7: =0 -> 0 | L7: =C7+D7+E7+G7+H7+I7+J7+K7 -> 4888.2463 | M7: =M6+L7 -> -49400.814 | N7: =L7 -> 4888.2463 | O7: =O6+N7 -> 1189.9863
A8: 2 | B8: =Supuestos!$B$32*Supuestos!$B$47 -> 18 | C8: =B8*Supuestos!$B$7 -> 4482 | D8: =-C8*Supuestos!$B$8 -> -1344.6 | E8: =-B8*Supuestos!$B$19*Supuestos!$B$18 -> -15.48 | F8: =F7*(1-Supuestos!$B$14)+B8*Supuestos!$B$13 -> 3.75 | G8: =F8*Supuestos!$B$9 -> 183.75 | H8: =-F8*Supuestos!$B$39 -> -20.7234 | I8: =-F8*Supuestos!$B$40 -> -9.84375 | J8: =-Supuestos!$B$42 -> -437.5 | K8: =0 -> 0 | L8: =C8+D8+E8+G8+H8+I8+J8+K8 -> 2837.6029 | M8: =M7+L8 -> -46563.211 | N8: =L8 -> 2837.6029 | O8: =O7+N8 -> 4027.5891
A9: 3 | B9: =Supuestos!$B$32*Supuestos!$B$48 -> 12 | C9: =B9*Supuestos!$B$7 -> 2988 | D9: =-C9*Supuestos!$B$8 -> -896.4 | E9: =-B9*Supuestos!$B$19*Supuestos!$B$18 -> -10.32 | F9: =F8*(1-Supuestos!$B$14)+B9*Supuestos!$B$13 -> 3.6375 | G9: =F9*Supuestos!$B$9 -> 178.2375 | H9: =-F9*Supuestos!$B$39 -> -20.101698 | I9: =-F9*Supuestos!$B$40 -> -9.5484375 | J9: =-Supuestos!$B$42 -> -437.5 | K9: =0 -> 0 | L9: =C9+D9+E9+G9+H9+I9+J9+K9 -> 1792.3674 | M9: =M8+L9 -> -44770.844 | N9: =L9 -> 1792.3674 | O9: =O8+N9 -> 5819.9565
A10: 4 | B10: =Supuestos!$B$32*Supuestos!$B$49 -> 9 | C10: =B10*Supuestos!$B$7 -> 2241 | D10: =-C10*Supuestos!$B$8 -> -672.3 | E10: =-B10*Supuestos!$B$19*Supuestos!$B$18 -> -7.74 | F10: =F9*(1-Supuestos!$B$14)+B10*Supuestos!$B$13 -> 3.264375 | G10: =F10*Supuestos!$B$9 -> 159.95437 | H10: =-F10*Supuestos!$B$39 -> -18.03972 | I10: =-F10*Supuestos!$B$40 -> -8.5689844 | J10: =-Supuestos!$B$42 -> -437.5 | K10: =0 -> 0 | L10: =C10+D10+E10+G10+H10+I10+J10+K10 -> 1256.8057 | M10: =M9+L10 -> -43514.038 | N10: =L10 -> 1256.8057 | O10: =O9+N10 -> 7076.7622
A11: 5 | B11: =Supuestos!$B$32*Supuestos!$B$50 -> 9 | C11: =B11*Supuestos!$B$7 -> 2241 | D11: =-C11*Supuestos!$B$8 -> -672.3 | E11: =-B11*Supuestos!$B$19*Supuestos!$B$18 -> -7.74 | F11: =F10*(1-Supuestos!$B$14)+B11*Supuestos!$B$13 -> 3.0218437 | G11: =F11*Supuestos!$B$9 -> 148.07034 | H11: =-F11*Supuestos!$B$39 -> -16.699434 | I11: =-F11*Supuestos!$B$40 -> -7.9323398 | J11: =-Supuestos!$B$42 -> -437.5 | K11: =0 -> 0 | L11: =C11+D11+E11+G11+H11+I11+J11+K11 -> 1246.8986 | M11: =M10+L11 -> -42267.139 | N11: =L11 -> 1246.8986 | O11: =O10+N11 -> 8323.6607
A12: 6 | B12: =Supuestos!$B$32*Supuestos!$B$51 -> 15 | C12: =B12*Supuestos!$B$7 -> 3735 | D12: =-C12*Supuestos!$B$8 -> -1120.5 | E12: =-B12*Supuestos!$B$19*Supuestos!$B$18 -> -12.9 | F12: =F11*(1-Supuestos!$B$14)+B12*Supuestos!$B$13 -> 3.4641984 | G12: =F12*Supuestos!$B$9 -> 169.74572 | H12: =-F12*Supuestos!$B$39 -> -19.143992 | I12: =-F12*Supuestos!$B$40 -> -9.0935209 | J12: =-Supuestos!$B$42 -> -437.5 | K12: =0 -> 0 | L12: =C12+D12+E12+G12+H12+I12+J12+K12 -> 2305.6082 | M12: =M11+L12 -> -39961.531 | N12: =L12 -> 2305.6082 | O12: =O11+N12 -> 10629.269
A13: 7 | B13: =Supuestos!$B$32*Supuestos!$B$52 -> 12 | C13: =B13*Supuestos!$B$7 -> 2988 | D13: =-C13*Supuestos!$B$8 -> -896.4 | E13: =-B13*Supuestos!$B$19*Supuestos!$B$18 -> -10.32 | F13: =F12*(1-Supuestos!$B$14)+B13*Supuestos!$B$13 -> 3.451729 | G13: =F13*Supuestos!$B$9 -> 169.13472 | H13: =-F13*Supuestos!$B$39 -> -19.075083 | I13: =-F13*Supuestos!$B$40 -> -9.0607886 | J13: =-Supuestos!$B$42 -> -437.5 | K13: =0 -> 0 | L13: =C13+D13+E13+G13+H13+I13+J13+K13 -> 1784.7788 | M13: =M12+L13 -> -38176.752 | N13: =L13 -> 1784.7788 | O13: =O12+N13 -> 12414.048
A14: 8 | B14: =Supuestos!$B$32*Supuestos!$B$53 -> 9 | C14: =B14*Supuestos!$B$7 -> 2241 | D14: =-C14*Supuestos!$B$8 -> -672.3 | E14: =-B14*Supuestos!$B$19*Supuestos!$B$18 -> -7.74 | F14: =F13*(1-Supuestos!$B$14)+B14*Supuestos!$B$13 -> 3.1436238 | G14: =F14*Supuestos!$B$9 -> 154.03757 | H14: =-F14*Supuestos!$B$39 -> -17.37242 | I14: =-F14*Supuestos!$B$40 -> -8.2520126 | J14: =-Supuestos!$B$42 -> -437.5 | K14: =0 -> 0 | L14: =C14+D14+E14+G14+H14+I14+J14+K14 -> 1251.8731 | M14: =M13+L14 -> -36924.879 | N14: =L14 -> 1251.8731 | O14: =O13+N14 -> 13665.921
A15: 9 | B15: =Supuestos!$B$32*Supuestos!$B$54 -> 7.5 | C15: =B15*Supuestos!$B$7 -> 1867.5 | D15: =-C15*Supuestos!$B$8 -> -560.25 | E15: =-B15*Supuestos!$B$19*Supuestos!$B$18 -> -6.45 | F15: =F14*(1-Supuestos!$B$14)+B15*Supuestos!$B$13 -> 2.7933555 | G15: =F15*Supuestos!$B$9 -> 136.87442 | H15: =-F15*Supuestos!$B$39 -> -15.436753 | I15: =-F15*Supuestos!$B$40 -> -7.3325582 | J15: =-Supuestos!$B$42 -> -437.5 | K15: =0 -> 0 | L15: =C15+D15+E15+G15+H15+I15+J15+K15 -> 977.40511 | M15: =M14+L15 -> -35947.474 | N15: =L15 -> 977.40511 | O15: =O14+N15 -> 14643.326
A16: 10 | B16: =Supuestos!$B$32*Supuestos!$B$55 -> 7.5 | C16: =B16*Supuestos!$B$7 -> 1867.5 | D16: =-C16*Supuestos!$B$8 -> -560.25 | E16: =-B16*Supuestos!$B$19*Supuestos!$B$18 -> -6.45 | F16: =F15*(1-Supuestos!$B$14)+B16*Supuestos!$B$13 -> 2.5656811 | G16: =F16*Supuestos!$B$9 -> 125.71837 | H16: =-F16*Supuestos!$B$39 -> -14.178569 | I16: =-F16*Supuestos!$B$40 -> -6.7349128 | J16: =-Supuestos!$B$42 -> -437.5 | K16: =0 -> 0 | L16: =C16+D16+E16+G16+H16+I16+J16+K16 -> 968.10489 | M16: =M15+L16 -> -34979.369 | N16: =L16 -> 968.10489 | O16: =O15+N16 -> 15611.431
A17: 11 | B17: =Supuestos!$B$32*Supuestos!$B$56 -> 9 | C17: =B17*Supuestos!$B$7 -> 2241 | D17: =-C17*Supuestos!$B$8 -> -672.3 | E17: =-B17*Supuestos!$B$19*Supuestos!$B$18 -> -7.74 | F17: =F16*(1-Supuestos!$B$14)+B17*Supuestos!$B$13 -> 2.5676927 | G17: =F17*Supuestos!$B$9 -> 125.81694 | H17: =-F17*Supuestos!$B$39 -> -14.189686 | I17: =-F17*Supuestos!$B$40 -> -6.7401933 | J17: =-Supuestos!$B$42 -> -437.5 | K17: =0 -> 0 | L17: =C17+D17+E17+G17+H17+I17+J17+K17 -> 1228.3471 | M17: =M16+L17 -> -33751.022 | N17: =L17 -> 1228.3471 | O17: =O16+N17 -> 16839.778
A18: 12 | B18: =Supuestos!$B$32*Supuestos!$B$57 -> 12 | C18: =B18*Supuestos!$B$7 -> 2988 | D18: =-C18*Supuestos!$B$8 -> -896.4 | E18: =-B18*Supuestos!$B$19*Supuestos!$B$18 -> -10.32 | F18: =F17*(1-Supuestos!$B$14)+B18*Supuestos!$B$13 -> 2.8690003 | G18: =F18*Supuestos!$B$9 -> 140.58101 | H18: =-F18*Supuestos!$B$39 -> -15.854784 | I18: =-F18*Supuestos!$B$40 -> -7.5311257 | J18: =-Supuestos!$B$42 -> -437.5 | K18: =0 -> 0 | L18: =C18+D18+E18+G18+H18+I18+J18+K18 -> 1760.9751 | M18: =M17+L18 -> -31990.047 | N18: =L18 -> 1760.9751 | O18: =O17+N18 -> 18600.753
A19: VPN 12 meses (contando horas) | C19: =NPV(Supuestos!$B$37,L7:L18)+L6 -> -33289.101 | E19: VPN solo efectivo | G19: =NPV(Supuestos!$B$37,N7:N18)+N6 -> 17301.699 | I19: TIR mensual (contando horas) | K19: =IF(SUM(L6:L18)<0,"no se recupera",IFERROR(IRR(L6:L18),"no hay")) -> no se recupera
A20: Mes en que el acumulado se vuelve positivo | C20: =IFERROR(INDEX(A6:A18,MATCH(1,INDEX(--(M6:M18>=0),0),0)),"no en 12 meses") -> no en 12 meses | E20: Mes positivo (efectivo) | G20: =IFERROR(INDEX(A6:A18,MATCH(1,INDEX(--(O6:O18>=0),0),0)),"no en 12 meses") -> 1 | I20: Ingreso total año 1 | K20: =SUM(C6:C18)+SUM(G6:G18) -> 39188.921
A23: ="MVP · escenario base — copias en el año 1: "&TEXT(Supuestos!$B$33,"#,##0") -> MVP · escenario base — copias en el año 1: 400
A24: Mes | B24: Copias vendidas | C24: Ventas del juego | D24: Comisión Steam | E24: IA de jugadores | F24: Suscriptores Pro (fin de mes) | G24: Ventas de Pro | H24: Comisión pasarela | I24: IA de Pro | J24: Supabase Pro | K24: Inversión | L24: FLUJO NETO | M24: Acumulado | N24: Flujo solo efectivo | O24: Acumulado efectivo
A25: 0 | B25: =0 -> 0 | C25: =B25*Supuestos!$B$7 -> 0 | D25: =-C25*Supuestos!$B$8 -> 0 | E25: =-B25*Supuestos!$B$19*Supuestos!$B$18 -> 0 | F25: =0 -> 0 | G25: =F25*Supuestos!$B$9 -> 0 | H25: =-F25*Supuestos!$B$39 -> 0 | I25: =-F25*Supuestos!$B$40 -> 0 | J25: =0 -> 0 | K25: =-(Supuestos!$B$21+Supuestos!$B$41) -> -54289.06 | L25: =C25+D25+E25+G25+H25+I25+J25+K25 -> -54289.06 | M25: =L25 -> -54289.06 | N25: =L25-K25-(Supuestos!$B$41+Supuestos!$B$23) -> -3698.26 | O25: =N25 -> -3698.26
A26: 1 | B26: =Supuestos!$B$33*Supuestos!$B$46 -> 80 | C26: =B26*Supuestos!$B$7 -> 19920 | D26: =-C26*Supuestos!$B$8 -> -5976 | E26: =-B26*Supuestos!$B$19*Supuestos!$B$18 -> -68.8 | F26: =F25*(1-Supuestos!$B$14)+B26*Supuestos!$B$13 -> 8 | G26: =F26*Supuestos!$B$9 -> 392 | H26: =-F26*Supuestos!$B$39 -> -44.20992 | I26: =-F26*Supuestos!$B$40 -> -21 | J26: =-Supuestos!$B$42 -> -437.5 | K26: =0 -> 0 | L26: =C26+D26+E26+G26+H26+I26+J26+K26 -> 13764.49 | M26: =M25+L26 -> -40524.57 | N26: =L26 -> 13764.49 | O26: =O25+N26 -> 10066.23
A27: 2 | B27: =Supuestos!$B$33*Supuestos!$B$47 -> 48 | C27: =B27*Supuestos!$B$7 -> 11952 | D27: =-C27*Supuestos!$B$8 -> -3585.6 | E27: =-B27*Supuestos!$B$19*Supuestos!$B$18 -> -41.28 | F27: =F26*(1-Supuestos!$B$14)+B27*Supuestos!$B$13 -> 10 | G27: =F27*Supuestos!$B$9 -> 490 | H27: =-F27*Supuestos!$B$39 -> -55.2624 | I27: =-F27*Supuestos!$B$40 -> -26.25 | J27: =-Supuestos!$B$42 -> -437.5 | K27: =0 -> 0 | L27: =C27+D27+E27+G27+H27+I27+J27+K27 -> 8296.1076 | M27: =M26+L27 -> -32228.462 | N27: =L27 -> 8296.1076 | O27: =O26+N27 -> 18362.338
A28: 3 | B28: =Supuestos!$B$33*Supuestos!$B$48 -> 32 | C28: =B28*Supuestos!$B$7 -> 7968 | D28: =-C28*Supuestos!$B$8 -> -2390.4 | E28: =-B28*Supuestos!$B$19*Supuestos!$B$18 -> -27.52 | F28: =F27*(1-Supuestos!$B$14)+B28*Supuestos!$B$13 -> 9.7 | G28: =F28*Supuestos!$B$9 -> 475.3 | H28: =-F28*Supuestos!$B$39 -> -53.604528 | I28: =-F28*Supuestos!$B$40 -> -25.4625 | J28: =-Supuestos!$B$42 -> -437.5 | K28: =0 -> 0 | L28: =C28+D28+E28+G28+H28+I28+J28+K28 -> 5508.813 | M28: =M27+L28 -> -26719.649 | N28: =L28 -> 5508.813 | O28: =O27+N28 -> 23871.151
A29: 4 | B29: =Supuestos!$B$33*Supuestos!$B$49 -> 24 | C29: =B29*Supuestos!$B$7 -> 5976 | D29: =-C29*Supuestos!$B$8 -> -1792.8 | E29: =-B29*Supuestos!$B$19*Supuestos!$B$18 -> -20.64 | F29: =F28*(1-Supuestos!$B$14)+B29*Supuestos!$B$13 -> 8.705 | G29: =F29*Supuestos!$B$9 -> 426.545 | H29: =-F29*Supuestos!$B$39 -> -48.105919 | I29: =-F29*Supuestos!$B$40 -> -22.850625 | J29: =-Supuestos!$B$42 -> -437.5 | K29: =0 -> 0 | L29: =C29+D29+E29+G29+H29+I29+J29+K29 -> 4080.6485 | M29: =M28+L29 -> -22639.001 | N29: =L29 -> 4080.6485 | O29: =O28+N29 -> 27951.799
A30: 5 | B30: =Supuestos!$B$33*Supuestos!$B$50 -> 24 | C30: =B30*Supuestos!$B$7 -> 5976 | D30: =-C30*Supuestos!$B$8 -> -1792.8 | E30: =-B30*Supuestos!$B$19*Supuestos!$B$18 -> -20.64 | F30: =F29*(1-Supuestos!$B$14)+B30*Supuestos!$B$13 -> 8.05825 | G30: =F30*Supuestos!$B$9 -> 394.85425 | H30: =-F30*Supuestos!$B$39 -> -44.531823 | I30: =-F30*Supuestos!$B$40 -> -21.152906 | J30: =-Supuestos!$B$42 -> -437.5 | K30: =0 -> 0 | L30: =C30+D30+E30+G30+H30+I30+J30+K30 -> 4054.2295 | M30: =M29+L30 -> -18584.771 | N30: =L30 -> 4054.2295 | O30: =O29+N30 -> 32006.029
A31: 6 | B31: =Supuestos!$B$33*Supuestos!$B$51 -> 40 | C31: =B31*Supuestos!$B$7 -> 9960 | D31: =-C31*Supuestos!$B$8 -> -2988 | E31: =-B31*Supuestos!$B$19*Supuestos!$B$18 -> -34.4 | F31: =F30*(1-Supuestos!$B$14)+B31*Supuestos!$B$13 -> 9.2378625 | G31: =F31*Supuestos!$B$9 -> 452.65526 | H31: =-F31*Supuestos!$B$39 -> -51.050645 | I31: =-F31*Supuestos!$B$40 -> -24.249389 | J31: =-Supuestos!$B$42 -> -437.5 | K31: =0 -> 0 | L31: =C31+D31+E31+G31+H31+I31+J31+K31 -> 6877.4552 | M31: =M30+L31 -> -11707.316 | N31: =L31 -> 6877.4552 | O31: =O30+N31 -> 38883.484
A32: 7 | B32: =Supuestos!$B$33*Supuestos!$B$52 -> 32 | C32: =B32*Supuestos!$B$7 -> 7968 | D32: =-C32*Supuestos!$B$8 -> -2390.4 | E32: =-B32*Supuestos!$B$19*Supuestos!$B$18 -> -27.52 | F32: =F31*(1-Supuestos!$B$14)+B32*Supuestos!$B$13 -> 9.2046106 | G32: =F32*Supuestos!$B$9 -> 451.02592 | H32: =-F32*Supuestos!$B$39 -> -50.866887 | I32: =-F32*Supuestos!$B$40 -> -24.162103 | J32: =-Supuestos!$B$42 -> -437.5 | K32: =0 -> 0 | L32: =C32+D32+E32+G32+H32+I32+J32+K32 -> 5488.5769 | M32: =M31+L32 -> -6218.7392 | N32: =L32 -> 5488.5769 | O32: =O31+N32 -> 44372.061
A33: 8 | B33: =Supuestos!$B$33*Supuestos!$B$53 -> 24 | C33: =B33*Supuestos!$B$7 -> 5976 | D33: =-C33*Supuestos!$B$8 -> -1792.8 | E33: =-B33*Supuestos!$B$19*Supuestos!$B$18 -> -20.64 | F33: =F32*(1-Supuestos!$B$14)+B33*Supuestos!$B$13 -> 8.3829969 | G33: =F33*Supuestos!$B$9 -> 410.76685 | H33: =-F33*Supuestos!$B$39 -> -46.326453 | I33: =-F33*Supuestos!$B$40 -> -22.005367 | J33: =-Supuestos!$B$42 -> -437.5 | K33: =0 -> 0 | L33: =C33+D33+E33+G33+H33+I33+J33+K33 -> 4067.495 | M33: =M32+L33 -> -2151.2442 | N33: =L33 -> 4067.495 | O33: =O32+N33 -> 48439.556
A34: 9 | B34: =Supuestos!$B$33*Supuestos!$B$54 -> 20 | C34: =B34*Supuestos!$B$7 -> 4980 | D34: =-C34*Supuestos!$B$8 -> -1494 | E34: =-B34*Supuestos!$B$19*Supuestos!$B$18 -> -17.2 | F34: =F33*(1-Supuestos!$B$14)+B34*Supuestos!$B$13 -> 7.448948 | G34: =F34*Supuestos!$B$9 -> 364.99845 | H34: =-F34*Supuestos!$B$39 -> -41.164674 | I34: =-F34*Supuestos!$B$40 -> -19.553488 | J34: =-Supuestos!$B$42 -> -437.5 | K34: =0 -> 0 | L34: =C34+D34+E34+G34+H34+I34+J34+K34 -> 3335.5803 | M34: =M33+L34 -> 1184.3361 | N34: =L34 -> 3335.5803 | O34: =O33+N34 -> 51775.136
A35: 10 | B35: =Supuestos!$B$33*Supuestos!$B$55 -> 20 | C35: =B35*Supuestos!$B$7 -> 4980 | D35: =-C35*Supuestos!$B$8 -> -1494 | E35: =-B35*Supuestos!$B$19*Supuestos!$B$18 -> -17.2 | F35: =F34*(1-Supuestos!$B$14)+B35*Supuestos!$B$13 -> 6.8418162 | G35: =F35*Supuestos!$B$9 -> 335.24899 | H35: =-F35*Supuestos!$B$39 -> -37.809518 | I35: =-F35*Supuestos!$B$40 -> -17.959768 | J35: =-Supuestos!$B$42 -> -437.5 | K35: =0 -> 0 | L35: =C35+D35+E35+G35+H35+I35+J35+K35 -> 3310.7797 | M35: =M34+L35 -> 4495.1158 | N35: =L35 -> 3310.7797 | O35: =O34+N35 -> 55085.916
A36: 11 | B36: =Supuestos!$B$33*Supuestos!$B$56 -> 24 | C36: =B36*Supuestos!$B$7 -> 5976 | D36: =-C36*Supuestos!$B$8 -> -1792.8 | E36: =-B36*Supuestos!$B$19*Supuestos!$B$18 -> -20.64 | F36: =F35*(1-Supuestos!$B$14)+B36*Supuestos!$B$13 -> 6.8471805 | G36: =F36*Supuestos!$B$9 -> 335.51185 | H36: =-F36*Supuestos!$B$39 -> -37.839163 | I36: =-F36*Supuestos!$B$40 -> -17.973849 | J36: =-Supuestos!$B$42 -> -437.5 | K36: =0 -> 0 | L36: =C36+D36+E36+G36+H36+I36+J36+K36 -> 4004.7588 | M36: =M35+L36 -> 8499.8746 | N36: =L36 -> 4004.7588 | O36: =O35+N36 -> 59090.675
A37: 12 | B37: =Supuestos!$B$33*Supuestos!$B$57 -> 32 | C37: =B37*Supuestos!$B$7 -> 7968 | D37: =-C37*Supuestos!$B$8 -> -2390.4 | E37: =-B37*Supuestos!$B$19*Supuestos!$B$18 -> -27.52 | F37: =F36*(1-Supuestos!$B$14)+B37*Supuestos!$B$13 -> 7.6506673 | G37: =F37*Supuestos!$B$9 -> 374.8827 | H37: =-F37*Supuestos!$B$39 -> -42.279424 | I37: =-F37*Supuestos!$B$40 -> -20.083002 | J37: =-Supuestos!$B$42 -> -437.5 | K37: =0 -> 0 | L37: =C37+D37+E37+G37+H37+I37+J37+K37 -> 5425.1003 | M37: =M36+L37 -> 13924.975 | N37: =L37 -> 5425.1003 | O37: =O36+N37 -> 64515.775
A38: VPN 12 meses (contando horas) | C38: =NPV(Supuestos!$B$37,L26:L37)+L25 -> 9829.4277 | E38: VPN solo efectivo | G38: =NPV(Supuestos!$B$37,N26:N37)+N25 -> 60420.228 | I38: TIR mensual (contando horas) | K38: =IF(SUM(L25:L37)<0,"no se recupera",IFERROR(IRR(L25:L37),"no hay")) -> 0.045797956
A39: Mes en que el acumulado se vuelve positivo | C39: =IFERROR(INDEX(A25:A37,MATCH(1,INDEX(--(M25:M37>=0),0),0)),"no en 12 meses") -> 9 | E39: Mes positivo (efectivo) | G39: =IFERROR(INDEX(A25:A37,MATCH(1,INDEX(--(O25:O37>=0),0),0)),"no en 12 meses") -> 1 | I39: Ingreso total año 1 | K39: =SUM(C25:C37)+SUM(G25:G37) -> 104503.79
A42: ="MVP · escenario optimista — copias en el año 1: "&TEXT(Supuestos!$B$34,"#,##0") -> MVP · escenario optimista — copias en el año 1: 1,100
A43: Mes | B43: Copias vendidas | C43: Ventas del juego | D43: Comisión Steam | E43: IA de jugadores | F43: Suscriptores Pro (fin de mes) | G43: Ventas de Pro | H43: Comisión pasarela | I43: IA de Pro | J43: Supabase Pro | K43: Inversión | L43: FLUJO NETO | M43: Acumulado | N43: Flujo solo efectivo | O43: Acumulado efectivo
A44: 0 | B44: =0 -> 0 | C44: =B44*Supuestos!$B$7 -> 0 | D44: =-C44*Supuestos!$B$8 -> 0 | E44: =-B44*Supuestos!$B$19*Supuestos!$B$18 -> 0 | F44: =0 -> 0 | G44: =F44*Supuestos!$B$9 -> 0 | H44: =-F44*Supuestos!$B$39 -> 0 | I44: =-F44*Supuestos!$B$40 -> 0 | J44: =0 -> 0 | K44: =-(Supuestos!$B$21+Supuestos!$B$41) -> -54289.06 | L44: =C44+D44+E44+G44+H44+I44+J44+K44 -> -54289.06 | M44: =L44 -> -54289.06 | N44: =L44-K44-(Supuestos!$B$41+Supuestos!$B$23) -> -3698.26 | O44: =N44 -> -3698.26
A45: 1 | B45: =Supuestos!$B$34*Supuestos!$B$46 -> 220 | C45: =B45*Supuestos!$B$7 -> 54780 | D45: =-C45*Supuestos!$B$8 -> -16434 | E45: =-B45*Supuestos!$B$19*Supuestos!$B$18 -> -189.2 | F45: =F44*(1-Supuestos!$B$14)+B45*Supuestos!$B$13 -> 22 | G45: =F45*Supuestos!$B$9 -> 1078 | H45: =-F45*Supuestos!$B$39 -> -121.57728 | I45: =-F45*Supuestos!$B$40 -> -57.75 | J45: =-Supuestos!$B$42 -> -437.5 | K45: =0 -> 0 | L45: =C45+D45+E45+G45+H45+I45+J45+K45 -> 38617.973 | M45: =M44+L45 -> -15671.087 | N45: =L45 -> 38617.973 | O45: =O44+N45 -> 34919.713
A46: 2 | B46: =Supuestos!$B$34*Supuestos!$B$47 -> 132 | C46: =B46*Supuestos!$B$7 -> 32868 | D46: =-C46*Supuestos!$B$8 -> -9860.4 | E46: =-B46*Supuestos!$B$19*Supuestos!$B$18 -> -113.52 | F46: =F45*(1-Supuestos!$B$14)+B46*Supuestos!$B$13 -> 27.5 | G46: =F46*Supuestos!$B$9 -> 1347.5 | H46: =-F46*Supuestos!$B$39 -> -151.9716 | I46: =-F46*Supuestos!$B$40 -> -72.1875 | J46: =-Supuestos!$B$42 -> -437.5 | K46: =0 -> 0 | L46: =C46+D46+E46+G46+H46+I46+J46+K46 -> 23579.921 | M46: =M45+L46 -> 7908.8336 | N46: =L46 -> 23579.921 | O46: =O45+N46 -> 58499.634
A47: 3 | B47: =Supuestos!$B$34*Supuestos!$B$48 -> 88 | C47: =B47*Supuestos!$B$7 -> 21912 | D47: =-C47*Supuestos!$B$8 -> -6573.6 | E47: =-B47*Supuestos!$B$19*Supuestos!$B$18 -> -75.68 | F47: =F46*(1-Supuestos!$B$14)+B47*Supuestos!$B$13 -> 26.675 | G47: =F47*Supuestos!$B$9 -> 1307.075 | H47: =-F47*Supuestos!$B$39 -> -147.41245 | I47: =-F47*Supuestos!$B$40 -> -70.021875 | J47: =-Supuestos!$B$42 -> -437.5 | K47: =0 -> 0 | L47: =C47+D47+E47+G47+H47+I47+J47+K47 -> 15914.861 | M47: =M46+L47 -> 23823.694 | N47: =L47 -> 15914.861 | O47: =O46+N47 -> 74414.494
A48: 4 | B48: =Supuestos!$B$34*Supuestos!$B$49 -> 66 | C48: =B48*Supuestos!$B$7 -> 16434 | D48: =-C48*Supuestos!$B$8 -> -4930.2 | E48: =-B48*Supuestos!$B$19*Supuestos!$B$18 -> -56.76 | F48: =F47*(1-Supuestos!$B$14)+B48*Supuestos!$B$13 -> 23.93875 | G48: =F48*Supuestos!$B$9 -> 1172.9987 | H48: =-F48*Supuestos!$B$39 -> -132.29128 | I48: =-F48*Supuestos!$B$40 -> -62.839219 | J48: =-Supuestos!$B$42 -> -437.5 | K48: =0 -> 0 | L48: =C48+D48+E48+G48+H48+I48+J48+K48 -> 11987.408 | M48: =M47+L48 -> 35811.103 | N48: =L48 -> 11987.408 | O48: =O47+N48 -> 86401.903
A49: 5 | B49: =Supuestos!$B$34*Supuestos!$B$50 -> 66 | C49: =B49*Supuestos!$B$7 -> 16434 | D49: =-C49*Supuestos!$B$8 -> -4930.2 | E49: =-B49*Supuestos!$B$19*Supuestos!$B$18 -> -56.76 | F49: =F48*(1-Supuestos!$B$14)+B49*Supuestos!$B$13 -> 22.160187 | G49: =F49*Supuestos!$B$9 -> 1085.8492 | H49: =-F49*Supuestos!$B$39 -> -122.46251 | I49: =-F49*Supuestos!$B$40 -> -58.170492 | J49: =-Supuestos!$B$42 -> -437.5 | K49: =0 -> 0 | L49: =C49+D49+E49+G49+H49+I49+J49+K49 -> 11914.756 | M49: =M48+L49 -> 47725.859 | N49: =L49 -> 11914.756 | O49: =O48+N49 -> 98316.659
A50: 6 | B50: =Supuestos!$B$34*Supuestos!$B$51 -> 110 | C50: =B50*Supuestos!$B$7 -> 27390 | D50: =-C50*Supuestos!$B$8 -> -8217 | E50: =-B50*Supuestos!$B$19*Supuestos!$B$18 -> -94.6 | F50: =F49*(1-Supuestos!$B$14)+B50*Supuestos!$B$13 -> 25.404122 | G50: =F50*Supuestos!$B$9 -> 1244.802 | H50: =-F50*Supuestos!$B$39 -> -140.38927 | I50: =-F50*Supuestos!$B$40 -> -66.68582 | J50: =-Supuestos!$B$42 -> -437.5 | K50: =0 -> 0 | L50: =C50+D50+E50+G50+H50+I50+J50+K50 -> 19678.627 | M50: =M49+L50 -> 67404.486 | N50: =L50 -> 19678.627 | O50: =O49+N50 -> 117995.29
A51: 7 | B51: =Supuestos!$B$34*Supuestos!$B$52 -> 88 | C51: =B51*Supuestos!$B$7 -> 21912 | D51: =-C51*Supuestos!$B$8 -> -6573.6 | E51: =-B51*Supuestos!$B$19*Supuestos!$B$18 -> -75.68 | F51: =F50*(1-Supuestos!$B$14)+B51*Supuestos!$B$13 -> 25.312679 | G51: =F51*Supuestos!$B$9 -> 1240.3213 | H51: =-F51*Supuestos!$B$39 -> -139.88394 | I51: =-F51*Supuestos!$B$40 -> -66.445783 | J51: =-Supuestos!$B$42 -> -437.5 | K51: =0 -> 0 | L51: =C51+D51+E51+G51+H51+I51+J51+K51 -> 15859.212 | M51: =M50+L51 -> 83263.697 | N51: =L51 -> 15859.212 | O51: =O50+N51 -> 133854.5
A52: 8 | B52: =Supuestos!$B$34*Supuestos!$B$53 -> 66 | C52: =B52*Supuestos!$B$7 -> 16434 | D52: =-C52*Supuestos!$B$8 -> -4930.2 | E52: =-B52*Supuestos!$B$19*Supuestos!$B$18 -> -56.76 | F52: =F51*(1-Supuestos!$B$14)+B52*Supuestos!$B$13 -> 23.053241 | G52: =F52*Supuestos!$B$9 -> 1129.6088 | H52: =-F52*Supuestos!$B$39 -> -127.39775 | I52: =-F52*Supuestos!$B$40 -> -60.514759 | J52: =-Supuestos!$B$42 -> -437.5 | K52: =0 -> 0 | L52: =C52+D52+E52+G52+H52+I52+J52+K52 -> 11951.236 | M52: =M51+L52 -> 95214.933 | N52: =L52 -> 11951.236 | O52: =O51+N52 -> 145805.73
A53: 9 | B53: =Supuestos!$B$34*Supuestos!$B$54 -> 55 | C53: =B53*Supuestos!$B$7 -> 13695 | D53: =-C53*Supuestos!$B$8 -> -4108.5 | E53: =-B53*Supuestos!$B$19*Supuestos!$B$18 -> -47.3 | F53: =F52*(1-Supuestos!$B$14)+B53*Supuestos!$B$13 -> 20.484607 | G53: =F53*Supuestos!$B$9 -> 1003.7457 | H53: =-F53*Supuestos!$B$39 -> -113.20285 | I53: =-F53*Supuestos!$B$40 -> -53.772093 | J53: =-Supuestos!$B$42 -> -437.5 | K53: =0 -> 0 | L53: =C53+D53+E53+G53+H53+I53+J53+K53 -> 9938.4708 | M53: =M52+L53 -> 105153.4 | N53: =L53 -> 9938.4708 | O53: =O52+N53 -> 155744.2
A54: 10 | B54: =Supuestos!$B$34*Supuestos!$B$55 -> 55 | C54: =B54*Supuestos!$B$7 -> 13695 | D54: =-C54*Supuestos!$B$8 -> -4108.5 | E54: =-B54*Supuestos!$B$19*Supuestos!$B$18 -> -47.3 | F54: =F53*(1-Supuestos!$B$14)+B54*Supuestos!$B$13 -> 18.814995 | G54: =F54*Supuestos!$B$9 -> 921.93473 | H54: =-F54*Supuestos!$B$39 -> -103.97618 | I54: =-F54*Supuestos!$B$40 -> -49.389361 | J54: =-Supuestos!$B$42 -> -437.5 | K54: =0 -> 0 | L54: =C54+D54+E54+G54+H54+I54+J54+K54 -> 9870.2692 | M54: =M53+L54 -> 115023.67 | N54: =L54 -> 9870.2692 | O54: =O53+N54 -> 165614.47
A55: 11 | B55: =Supuestos!$B$34*Supuestos!$B$56 -> 66 | C55: =B55*Supuestos!$B$7 -> 16434 | D55: =-C55*Supuestos!$B$8 -> -4930.2 | E55: =-B55*Supuestos!$B$19*Supuestos!$B$18 -> -56.76 | F55: =F54*(1-Supuestos!$B$14)+B55*Supuestos!$B$13 -> 18.829746 | G55: =F55*Supuestos!$B$9 -> 922.65758 | H55: =-F55*Supuestos!$B$39 -> -104.0577 | I55: =-F55*Supuestos!$B$40 -> -49.428084 | J55: =-Supuestos!$B$42 -> -437.5 | K55: =0 -> 0 | L55: =C55+D55+E55+G55+H55+I55+J55+K55 -> 11778.712 | M55: =M54+L55 -> 126802.39 | N55: =L55 -> 11778.712 | O55: =O54+N55 -> 177393.19
A56: 12 | B56: =Supuestos!$B$34*Supuestos!$B$57 -> 88 | C56: =B56*Supuestos!$B$7 -> 21912 | D56: =-C56*Supuestos!$B$8 -> -6573.6 | E56: =-B56*Supuestos!$B$19*Supuestos!$B$18 -> -75.68 | F56: =F55*(1-Supuestos!$B$14)+B56*Supuestos!$B$13 -> 21.039335 | G56: =F56*Supuestos!$B$9 -> 1030.9274 | H56: =-F56*Supuestos!$B$39 -> -116.26842 | I56: =-F56*Supuestos!$B$40 -> -55.228255 | J56: =-Supuestos!$B$42 -> -437.5 | K56: =0 -> 0 | L56: =C56+D56+E56+G56+H56+I56+J56+K56 -> 15684.651 | M56: =M55+L56 -> 142487.04 | N56: =L56 -> 15684.651 | O56: =O55+N56 -> 193077.84
A57: VPN 12 meses (contando horas) | C57: =NPV(Supuestos!$B$37,L45:L56)+L44 -> 130561.31 | E57: VPN solo efectivo | G57: =NPV(Supuestos!$B$37,N45:N56)+N44 -> 181152.11 | I57: TIR mensual (contando horas) | K57: =IF(SUM(L44:L56)<0,"no se recupera",IFERROR(IRR(L44:L56),"no hay")) -> 0.42943382
A58: Mes en que el acumulado se vuelve positivo | C58: =IFERROR(INDEX(A44:A56,MATCH(1,INDEX(--(M44:M56>=0),0),0)),"no en 12 meses") -> 2 | E58: Mes positivo (efectivo) | G58: =IFERROR(INDEX(A44:A56,MATCH(1,INDEX(--(O44:O56>=0),0),0)),"no en 12 meses") -> 1 | I58: Ingreso total año 1 | K58: =SUM(C44:C56)+SUM(G44:G56) -> 287385.42
A61: ="3 bloques · escenario pesimista — copias en el año 1: "&TEXT(Supuestos!$B$32,"#,##0") -> 3 bloques · escenario pesimista — copias en el año 1: 150
A62: Mes | B62: Copias vendidas | C62: Ventas del juego | D62: Comisión Steam | E62: IA de jugadores | F62: Suscriptores Pro (fin de mes) | G62: Ventas de Pro | H62: Comisión pasarela | I62: IA de Pro | J62: Supabase Pro | K62: Inversión | L62: FLUJO NETO | M62: Acumulado | N62: Flujo solo efectivo | O62: Acumulado efectivo
A63: 0 | B63: =0 -> 0 | C63: =B63*Supuestos!$B$7 -> 0 | D63: =-C63*Supuestos!$B$8 -> 0 | E63: =-B63*Supuestos!$B$20*Supuestos!$B$18 -> 0 | F63: =0 -> 0 | G63: =F63*Supuestos!$B$9 -> 0 | H63: =-F63*Supuestos!$B$39 -> 0 | I63: =-F63*Supuestos!$B$40 -> 0 | J63: =0 -> 0 | K63: =-(Supuestos!$B$22+Supuestos!$B$41) -> -119973.66 | L63: =C63+D63+E63+G63+H63+I63+J63+K63 -> -119973.66 | M63: =L63 -> -119973.66 | N63: =L63-K63-(Supuestos!$B$41+Supuestos!$B$24) -> -3722.46 | O63: =N63 -> -3722.46
A64: 1 | B64: =Supuestos!$B$32*Supuestos!$B$46 -> 30 | C64: =B64*Supuestos!$B$7 -> 7470 | D64: =-C64*Supuestos!$B$8 -> -2241 | E64: =-B64*Supuestos!$B$20*Supuestos!$B$18 -> -188.4 | F64: =F63*(1-Supuestos!$B$14)+B64*Supuestos!$B$13 -> 3 | G64: =F64*Supuestos!$B$9 -> 147 | H64: =-F64*Supuestos!$B$39 -> -16.57872 | I64: =-F64*Supuestos!$B$40 -> -7.875 | J64: =-Supuestos!$B$42 -> -437.5 | K64: =0 -> 0 | L64: =C64+D64+E64+G64+H64+I64+J64+K64 -> 4725.6463 | M64: =M63+L64 -> -115248.01 | N64: =L64 -> 4725.6463 | O64: =O63+N64 -> 1003.1863
A65: 2 | B65: =Supuestos!$B$32*Supuestos!$B$47 -> 18 | C65: =B65*Supuestos!$B$7 -> 4482 | D65: =-C65*Supuestos!$B$8 -> -1344.6 | E65: =-B65*Supuestos!$B$20*Supuestos!$B$18 -> -113.04 | F65: =F64*(1-Supuestos!$B$14)+B65*Supuestos!$B$13 -> 3.75 | G65: =F65*Supuestos!$B$9 -> 183.75 | H65: =-F65*Supuestos!$B$39 -> -20.7234 | I65: =-F65*Supuestos!$B$40 -> -9.84375 | J65: =-Supuestos!$B$42 -> -437.5 | K65: =0 -> 0 | L65: =C65+D65+E65+G65+H65+I65+J65+K65 -> 2740.0428 | M65: =M64+L65 -> -112507.97 | N65: =L65 -> 2740.0428 | O65: =O64+N65 -> 3743.2291
A66: 3 | B66: =Supuestos!$B$32*Supuestos!$B$48 -> 12 | C66: =B66*Supuestos!$B$7 -> 2988 | D66: =-C66*Supuestos!$B$8 -> -896.4 | E66: =-B66*Supuestos!$B$20*Supuestos!$B$18 -> -75.36 | F66: =F65*(1-Supuestos!$B$14)+B66*Supuestos!$B$13 -> 3.6375 | G66: =F66*Supuestos!$B$9 -> 178.2375 | H66: =-F66*Supuestos!$B$39 -> -20.101698 | I66: =-F66*Supuestos!$B$40 -> -9.5484375 | J66: =-Supuestos!$B$42 -> -437.5 | K66: =0 -> 0 | L66: =C66+D66+E66+G66+H66+I66+J66+K66 -> 1727.3274 | M66: =M65+L66 -> -110780.64 | N66: =L66 -> 1727.3274 | O66: =O65+N66 -> 5470.5565
A67: 4 | B67: =Supuestos!$B$32*Supuestos!$B$49 -> 9 | C67: =B67*Supuestos!$B$7 -> 2241 | D67: =-C67*Supuestos!$B$8 -> -672.3 | E67: =-B67*Supuestos!$B$20*Supuestos!$B$18 -> -56.52 | F67: =F66*(1-Supuestos!$B$14)+B67*Supuestos!$B$13 -> 3.264375 | G67: =F67*Supuestos!$B$9 -> 159.95437 | H67: =-F67*Supuestos!$B$39 -> -18.03972 | I67: =-F67*Supuestos!$B$40 -> -8.5689844 | J67: =-Supuestos!$B$42 -> -437.5 | K67: =0 -> 0 | L67: =C67+D67+E67+G67+H67+I67+J67+K67 -> 1208.0257 | M67: =M66+L67 -> -109572.62 | N67: =L67 -> 1208.0257 | O67: =O66+N67 -> 6678.5822
A68: 5 | B68: =Supuestos!$B$32*Supuestos!$B$50 -> 9 | C68: =B68*Supuestos!$B$7 -> 2241 | D68: =-C68*Supuestos!$B$8 -> -672.3 | E68: =-B68*Supuestos!$B$20*Supuestos!$B$18 -> -56.52 | F68: =F67*(1-Supuestos!$B$14)+B68*Supuestos!$B$13 -> 3.0218437 | G68: =F68*Supuestos!$B$9 -> 148.07034 | H68: =-F68*Supuestos!$B$39 -> -16.699434 | I68: =-F68*Supuestos!$B$40 -> -7.9323398 | J68: =-Supuestos!$B$42 -> -437.5 | K68: =0 -> 0 | L68: =C68+D68+E68+G68+H68+I68+J68+K68 -> 1198.1186 | M68: =M67+L68 -> -108374.5 | N68: =L68 -> 1198.1186 | O68: =O67+N68 -> 7876.7007
A69: 6 | B69: =Supuestos!$B$32*Supuestos!$B$51 -> 15 | C69: =B69*Supuestos!$B$7 -> 3735 | D69: =-C69*Supuestos!$B$8 -> -1120.5 | E69: =-B69*Supuestos!$B$20*Supuestos!$B$18 -> -94.2 | F69: =F68*(1-Supuestos!$B$14)+B69*Supuestos!$B$13 -> 3.4641984 | G69: =F69*Supuestos!$B$9 -> 169.74572 | H69: =-F69*Supuestos!$B$39 -> -19.143992 | I69: =-F69*Supuestos!$B$40 -> -9.0935209 | J69: =-Supuestos!$B$42 -> -437.5 | K69: =0 -> 0 | L69: =C69+D69+E69+G69+H69+I69+J69+K69 -> 2224.3082 | M69: =M68+L69 -> -106150.19 | N69: =L69 -> 2224.3082 | O69: =O68+N69 -> 10101.009
A70: 7 | B70: =Supuestos!$B$32*Supuestos!$B$52 -> 12 | C70: =B70*Supuestos!$B$7 -> 2988 | D70: =-C70*Supuestos!$B$8 -> -896.4 | E70: =-B70*Supuestos!$B$20*Supuestos!$B$18 -> -75.36 | F70: =F69*(1-Supuestos!$B$14)+B70*Supuestos!$B$13 -> 3.451729 | G70: =F70*Supuestos!$B$9 -> 169.13472 | H70: =-F70*Supuestos!$B$39 -> -19.075083 | I70: =-F70*Supuestos!$B$40 -> -9.0607886 | J70: =-Supuestos!$B$42 -> -437.5 | K70: =0 -> 0 | L70: =C70+D70+E70+G70+H70+I70+J70+K70 -> 1719.7388 | M70: =M69+L70 -> -104430.45 | N70: =L70 -> 1719.7388 | O70: =O69+N70 -> 11820.748
A71: 8 | B71: =Supuestos!$B$32*Supuestos!$B$53 -> 9 | C71: =B71*Supuestos!$B$7 -> 2241 | D71: =-C71*Supuestos!$B$8 -> -672.3 | E71: =-B71*Supuestos!$B$20*Supuestos!$B$18 -> -56.52 | F71: =F70*(1-Supuestos!$B$14)+B71*Supuestos!$B$13 -> 3.1436238 | G71: =F71*Supuestos!$B$9 -> 154.03757 | H71: =-F71*Supuestos!$B$39 -> -17.37242 | I71: =-F71*Supuestos!$B$40 -> -8.2520126 | J71: =-Supuestos!$B$42 -> -437.5 | K71: =0 -> 0 | L71: =C71+D71+E71+G71+H71+I71+J71+K71 -> 1203.0931 | M71: =M70+L71 -> -103227.36 | N71: =L71 -> 1203.0931 | O71: =O70+N71 -> 13023.841
A72: 9 | B72: =Supuestos!$B$32*Supuestos!$B$54 -> 7.5 | C72: =B72*Supuestos!$B$7 -> 1867.5 | D72: =-C72*Supuestos!$B$8 -> -560.25 | E72: =-B72*Supuestos!$B$20*Supuestos!$B$18 -> -47.1 | F72: =F71*(1-Supuestos!$B$14)+B72*Supuestos!$B$13 -> 2.7933555 | G72: =F72*Supuestos!$B$9 -> 136.87442 | H72: =-F72*Supuestos!$B$39 -> -15.436753 | I72: =-F72*Supuestos!$B$40 -> -7.3325582 | J72: =-Supuestos!$B$42 -> -437.5 | K72: =0 -> 0 | L72: =C72+D72+E72+G72+H72+I72+J72+K72 -> 936.75511 | M72: =M71+L72 -> -102290.6 | N72: =L72 -> 936.75511 | O72: =O71+N72 -> 13960.596
A73: 10 | B73: =Supuestos!$B$32*Supuestos!$B$55 -> 7.5 | C73: =B73*Supuestos!$B$7 -> 1867.5 | D73: =-C73*Supuestos!$B$8 -> -560.25 | E73: =-B73*Supuestos!$B$20*Supuestos!$B$18 -> -47.1 | F73: =F72*(1-Supuestos!$B$14)+B73*Supuestos!$B$13 -> 2.5656811 | G73: =F73*Supuestos!$B$9 -> 125.71837 | H73: =-F73*Supuestos!$B$39 -> -14.178569 | I73: =-F73*Supuestos!$B$40 -> -6.7349128 | J73: =-Supuestos!$B$42 -> -437.5 | K73: =0 -> 0 | L73: =C73+D73+E73+G73+H73+I73+J73+K73 -> 927.45489 | M73: =M72+L73 -> -101363.15 | N73: =L73 -> 927.45489 | O73: =O72+N73 -> 14888.051
A74: 11 | B74: =Supuestos!$B$32*Supuestos!$B$56 -> 9 | C74: =B74*Supuestos!$B$7 -> 2241 | D74: =-C74*Supuestos!$B$8 -> -672.3 | E74: =-B74*Supuestos!$B$20*Supuestos!$B$18 -> -56.52 | F74: =F73*(1-Supuestos!$B$14)+B74*Supuestos!$B$13 -> 2.5676927 | G74: =F74*Supuestos!$B$9 -> 125.81694 | H74: =-F74*Supuestos!$B$39 -> -14.189686 | I74: =-F74*Supuestos!$B$40 -> -6.7401933 | J74: =-Supuestos!$B$42 -> -437.5 | K74: =0 -> 0 | L74: =C74+D74+E74+G74+H74+I74+J74+K74 -> 1179.5671 | M74: =M73+L74 -> -100183.58 | N74: =L74 -> 1179.5671 | O74: =O73+N74 -> 16067.618
A75: 12 | B75: =Supuestos!$B$32*Supuestos!$B$57 -> 12 | C75: =B75*Supuestos!$B$7 -> 2988 | D75: =-C75*Supuestos!$B$8 -> -896.4 | E75: =-B75*Supuestos!$B$20*Supuestos!$B$18 -> -75.36 | F75: =F74*(1-Supuestos!$B$14)+B75*Supuestos!$B$13 -> 2.8690003 | G75: =F75*Supuestos!$B$9 -> 140.58101 | H75: =-F75*Supuestos!$B$39 -> -15.854784 | I75: =-F75*Supuestos!$B$40 -> -7.5311257 | J75: =-Supuestos!$B$42 -> -437.5 | K75: =0 -> 0 | L75: =C75+D75+E75+G75+H75+I75+J75+K75 -> 1695.9351 | M75: =M74+L75 -> -98487.647 | N75: =L75 -> 1695.9351 | O75: =O74+N75 -> 17763.553
A76: VPN 12 meses (contando horas) | C76: =NPV(Supuestos!$B$37,L64:L75)+L63 -> -99737.576 | E76: VPN solo efectivo | G76: =NPV(Supuestos!$B$37,N64:N75)+N63 -> 16513.624 | I76: TIR mensual (contando horas) | K76: =IF(SUM(L63:L75)<0,"no se recupera",IFERROR(IRR(L63:L75),"no hay")) -> no se recupera
A77: Mes en que el acumulado se vuelve positivo | C77: =IFERROR(INDEX(A63:A75,MATCH(1,INDEX(--(M63:M75>=0),0),0)),"no en 12 meses") -> no en 12 meses | E77: Mes positivo (efectivo) | G77: =IFERROR(INDEX(A63:A75,MATCH(1,INDEX(--(O63:O75>=0),0),0)),"no en 12 meses") -> 1 | I77: Ingreso total año 1 | K77: =SUM(C63:C75)+SUM(G63:G75) -> 39188.921
A80: ="3 bloques · escenario base — copias en el año 1: "&TEXT(Supuestos!$B$33,"#,##0") -> 3 bloques · escenario base — copias en el año 1: 400
A81: Mes | B81: Copias vendidas | C81: Ventas del juego | D81: Comisión Steam | E81: IA de jugadores | F81: Suscriptores Pro (fin de mes) | G81: Ventas de Pro | H81: Comisión pasarela | I81: IA de Pro | J81: Supabase Pro | K81: Inversión | L81: FLUJO NETO | M81: Acumulado | N81: Flujo solo efectivo | O81: Acumulado efectivo
A82: 0 | B82: =0 -> 0 | C82: =B82*Supuestos!$B$7 -> 0 | D82: =-C82*Supuestos!$B$8 -> 0 | E82: =-B82*Supuestos!$B$20*Supuestos!$B$18 -> 0 | F82: =0 -> 0 | G82: =F82*Supuestos!$B$9 -> 0 | H82: =-F82*Supuestos!$B$39 -> 0 | I82: =-F82*Supuestos!$B$40 -> 0 | J82: =0 -> 0 | K82: =-(Supuestos!$B$22+Supuestos!$B$41) -> -119973.66 | L82: =C82+D82+E82+G82+H82+I82+J82+K82 -> -119973.66 | M82: =L82 -> -119973.66 | N82: =L82-K82-(Supuestos!$B$41+Supuestos!$B$24) -> -3722.46 | O82: =N82 -> -3722.46
A83: 1 | B83: =Supuestos!$B$33*Supuestos!$B$46 -> 80 | C83: =B83*Supuestos!$B$7 -> 19920 | D83: =-C83*Supuestos!$B$8 -> -5976 | E83: =-B83*Supuestos!$B$20*Supuestos!$B$18 -> -502.4 | F83: =F82*(1-Supuestos!$B$14)+B83*Supuestos!$B$13 -> 8 | G83: =F83*Supuestos!$B$9 -> 392 | H83: =-F83*Supuestos!$B$39 -> -44.20992 | I83: =-F83*Supuestos!$B$40 -> -21 | J83: =-Supuestos!$B$42 -> -437.5 | K83: =0 -> 0 | L83: =C83+D83+E83+G83+H83+I83+J83+K83 -> 13330.89 | M83: =M82+L83 -> -106642.77 | N83: =L83 -> 13330.89 | O83: =O82+N83 -> 9608.4301
A84: 2 | B84: =Supuestos!$B$33*Supuestos!$B$47 -> 48 | C84: =B84*Supuestos!$B$7 -> 11952 | D84: =-C84*Supuestos!$B$8 -> -3585.6 | E84: =-B84*Supuestos!$B$20*Supuestos!$B$18 -> -301.44 | F84: =F83*(1-Supuestos!$B$14)+B84*Supuestos!$B$13 -> 10 | G84: =F84*Supuestos!$B$9 -> 490 | H84: =-F84*Supuestos!$B$39 -> -55.2624 | I84: =-F84*Supuestos!$B$40 -> -26.25 | J84: =-Supuestos!$B$42 -> -437.5 | K84: =0 -> 0 | L84: =C84+D84+E84+G84+H84+I84+J84+K84 -> 8035.9476 | M84: =M83+L84 -> -98606.822 | N84: =L84 -> 8035.9476 | O84: =O83+N84 -> 17644.378
A85: 3 | B85: =Supuestos!$B$33*Supuestos!$B$48 -> 32 | C85: =B85*Supuestos!$B$7 -> 7968 | D85: =-C85*Supuestos!$B$8 -> -2390.4 | E85: =-B85*Supuestos!$B$20*Supuestos!$B$18 -> -200.96 | F85: =F84*(1-Supuestos!$B$14)+B85*Supuestos!$B$13 -> 9.7 | G85: =F85*Supuestos!$B$9 -> 475.3 | H85: =-F85*Supuestos!$B$39 -> -53.604528 | I85: =-F85*Supuestos!$B$40 -> -25.4625 | J85: =-Supuestos!$B$42 -> -437.5 | K85: =0 -> 0 | L85: =C85+D85+E85+G85+H85+I85+J85+K85 -> 5335.373 | M85: =M84+L85 -> -93271.449 | N85: =L85 -> 5335.373 | O85: =O84+N85 -> 22979.751
A86: 4 | B86: =Supuestos!$B$33*Supuestos!$B$49 -> 24 | C86: =B86*Supuestos!$B$7 -> 5976 | D86: =-C86*Supuestos!$B$8 -> -1792.8 | E86: =-B86*Supuestos!$B$20*Supuestos!$B$18 -> -150.72 | F86: =F85*(1-Supuestos!$B$14)+B86*Supuestos!$B$13 -> 8.705 | G86: =F86*Supuestos!$B$9 -> 426.545 | H86: =-F86*Supuestos!$B$39 -> -48.105919 | I86: =-F86*Supuestos!$B$40 -> -22.850625 | J86: =-Supuestos!$B$42 -> -437.5 | K86: =0 -> 0 | L86: =C86+D86+E86+G86+H86+I86+J86+K86 -> 3950.5685 | M86: =M85+L86 -> -89320.881 | N86: =L86 -> 3950.5685 | O86: =O85+N86 -> 26930.319
A87: 5 | B87: =Supuestos!$B$33*Supuestos!$B$50 -> 24 | C87: =B87*Supuestos!$B$7 -> 5976 | D87: =-C87*Supuestos!$B$8 -> -1792.8 | E87: =-B87*Supuestos!$B$20*Supuestos!$B$18 -> -150.72 | F87: =F86*(1-Supuestos!$B$14)+B87*Supuestos!$B$13 -> 8.05825 | G87: =F87*Supuestos!$B$9 -> 394.85425 | H87: =-F87*Supuestos!$B$39 -> -44.531823 | I87: =-F87*Supuestos!$B$40 -> -21.152906 | J87: =-Supuestos!$B$42 -> -437.5 | K87: =0 -> 0 | L87: =C87+D87+E87+G87+H87+I87+J87+K87 -> 3924.1495 | M87: =M86+L87 -> -85396.731 | N87: =L87 -> 3924.1495 | O87: =O86+N87 -> 30854.469
A88: 6 | B88: =Supuestos!$B$33*Supuestos!$B$51 -> 40 | C88: =B88*Supuestos!$B$7 -> 9960 | D88: =-C88*Supuestos!$B$8 -> -2988 | E88: =-B88*Supuestos!$B$20*Supuestos!$B$18 -> -251.2 | F88: =F87*(1-Supuestos!$B$14)+B88*Supuestos!$B$13 -> 9.2378625 | G88: =F88*Supuestos!$B$9 -> 452.65526 | H88: =-F88*Supuestos!$B$39 -> -51.050645 | I88: =-F88*Supuestos!$B$40 -> -24.249389 | J88: =-Supuestos!$B$42 -> -437.5 | K88: =0 -> 0 | L88: =C88+D88+E88+G88+H88+I88+J88+K88 -> 6660.6552 | M88: =M87+L88 -> -78736.076 | N88: =L88 -> 6660.6552 | O88: =O87+N88 -> 37515.124
A89: 7 | B89: =Supuestos!$B$33*Supuestos!$B$52 -> 32 | C89: =B89*Supuestos!$B$7 -> 7968 | D89: =-C89*Supuestos!$B$8 -> -2390.4 | E89: =-B89*Supuestos!$B$20*Supuestos!$B$18 -> -200.96 | F89: =F88*(1-Supuestos!$B$14)+B89*Supuestos!$B$13 -> 9.2046106 | G89: =F89*Supuestos!$B$9 -> 451.02592 | H89: =-F89*Supuestos!$B$39 -> -50.866887 | I89: =-F89*Supuestos!$B$40 -> -24.162103 | J89: =-Supuestos!$B$42 -> -437.5 | K89: =0 -> 0 | L89: =C89+D89+E89+G89+H89+I89+J89+K89 -> 5315.1369 | M89: =M88+L89 -> -73420.939 | N89: =L89 -> 5315.1369 | O89: =O88+N89 -> 42830.261
A90: 8 | B90: =Supuestos!$B$33*Supuestos!$B$53 -> 24 | C90: =B90*Supuestos!$B$7 -> 5976 | D90: =-C90*Supuestos!$B$8 -> -1792.8 | E90: =-B90*Supuestos!$B$20*Supuestos!$B$18 -> -150.72 | F90: =F89*(1-Supuestos!$B$14)+B90*Supuestos!$B$13 -> 8.3829969 | G90: =F90*Supuestos!$B$9 -> 410.76685 | H90: =-F90*Supuestos!$B$39 -> -46.326453 | I90: =-F90*Supuestos!$B$40 -> -22.005367 | J90: =-Supuestos!$B$42 -> -437.5 | K90: =0 -> 0 | L90: =C90+D90+E90+G90+H90+I90+J90+K90 -> 3937.415 | M90: =M89+L90 -> -69483.524 | N90: =L90 -> 3937.415 | O90: =O89+N90 -> 46767.676
A91: 9 | B91: =Supuestos!$B$33*Supuestos!$B$54 -> 20 | C91: =B91*Supuestos!$B$7 -> 4980 | D91: =-C91*Supuestos!$B$8 -> -1494 | E91: =-B91*Supuestos!$B$20*Supuestos!$B$18 -> -125.6 | F91: =F90*(1-Supuestos!$B$14)+B91*Supuestos!$B$13 -> 7.448948 | G91: =F91*Supuestos!$B$9 -> 364.99845 | H91: =-F91*Supuestos!$B$39 -> -41.164674 | I91: =-F91*Supuestos!$B$40 -> -19.553488 | J91: =-Supuestos!$B$42 -> -437.5 | K91: =0 -> 0 | L91: =C91+D91+E91+G91+H91+I91+J91+K91 -> 3227.1803 | M91: =M90+L91 -> -66256.344 | N91: =L91 -> 3227.1803 | O91: =O90+N91 -> 49994.856
A92: 10 | B92: =Supuestos!$B$33*Supuestos!$B$55 -> 20 | C92: =B92*Supuestos!$B$7 -> 4980 | D92: =-C92*Supuestos!$B$8 -> -1494 | E92: =-B92*Supuestos!$B$20*Supuestos!$B$18 -> -125.6 | F92: =F91*(1-Supuestos!$B$14)+B92*Supuestos!$B$13 -> 6.8418162 | G92: =F92*Supuestos!$B$9 -> 335.24899 | H92: =-F92*Supuestos!$B$39 -> -37.809518 | I92: =-F92*Supuestos!$B$40 -> -17.959768 | J92: =-Supuestos!$B$42 -> -437.5 | K92: =0 -> 0 | L92: =C92+D92+E92+G92+H92+I92+J92+K92 -> 3202.3797 | M92: =M91+L92 -> -63053.964 | N92: =L92 -> 3202.3797 | O92: =O91+N92 -> 53197.236
A93: 11 | B93: =Supuestos!$B$33*Supuestos!$B$56 -> 24 | C93: =B93*Supuestos!$B$7 -> 5976 | D93: =-C93*Supuestos!$B$8 -> -1792.8 | E93: =-B93*Supuestos!$B$20*Supuestos!$B$18 -> -150.72 | F93: =F92*(1-Supuestos!$B$14)+B93*Supuestos!$B$13 -> 6.8471805 | G93: =F93*Supuestos!$B$9 -> 335.51185 | H93: =-F93*Supuestos!$B$39 -> -37.839163 | I93: =-F93*Supuestos!$B$40 -> -17.973849 | J93: =-Supuestos!$B$42 -> -437.5 | K93: =0 -> 0 | L93: =C93+D93+E93+G93+H93+I93+J93+K93 -> 3874.6788 | M93: =M92+L93 -> -59179.285 | N93: =L93 -> 3874.6788 | O93: =O92+N93 -> 57071.915
A94: 12 | B94: =Supuestos!$B$33*Supuestos!$B$57 -> 32 | C94: =B94*Supuestos!$B$7 -> 7968 | D94: =-C94*Supuestos!$B$8 -> -2390.4 | E94: =-B94*Supuestos!$B$20*Supuestos!$B$18 -> -200.96 | F94: =F93*(1-Supuestos!$B$14)+B94*Supuestos!$B$13 -> 7.6506673 | G94: =F94*Supuestos!$B$9 -> 374.8827 | H94: =-F94*Supuestos!$B$39 -> -42.279424 | I94: =-F94*Supuestos!$B$40 -> -20.083002 | J94: =-Supuestos!$B$42 -> -437.5 | K94: =0 -> 0 | L94: =C94+D94+E94+G94+H94+I94+J94+K94 -> 5251.6603 | M94: =M93+L94 -> -53927.625 | N94: =L94 -> 5251.6603 | O94: =O93+N94 -> 62323.575
A95: VPN 12 meses (contando horas) | C95: =NPV(Supuestos!$B$37,L83:L94)+L82 -> -57892.172 | E95: VPN solo efectivo | G95: =NPV(Supuestos!$B$37,N83:N94)+N82 -> 58359.028 | I95: TIR mensual (contando horas) | K95: =IF(SUM(L82:L94)<0,"no se recupera",IFERROR(IRR(L82:L94),"no hay")) -> no se recupera
A96: Mes en que el acumulado se vuelve positivo | C96: =IFERROR(INDEX(A82:A94,MATCH(1,INDEX(--(M82:M94>=0),0),0)),"no en 12 meses") -> no en 12 meses | E96: Mes positivo (efectivo) | G96: =IFERROR(INDEX(A82:A94,MATCH(1,INDEX(--(O82:O94>=0),0),0)),"no en 12 meses") -> 1 | I96: Ingreso total año 1 | K96: =SUM(C82:C94)+SUM(G82:G94) -> 104503.79
A99: ="3 bloques · escenario optimista — copias en el año 1: "&TEXT(Supuestos!$B$34,"#,##0") -> 3 bloques · escenario optimista — copias en el año 1: 1,100
A100: Mes | B100: Copias vendidas | C100: Ventas del juego | D100: Comisión Steam | E100: IA de jugadores | F100: Suscriptores Pro (fin de mes) | G100: Ventas de Pro | H100: Comisión pasarela | I100: IA de Pro | J100: Supabase Pro | K100: Inversión | L100: FLUJO NETO | M100: Acumulado | N100: Flujo solo efectivo | O100: Acumulado efectivo
A101: 0 | B101: =0 -> 0 | C101: =B101*Supuestos!$B$7 -> 0 | D101: =-C101*Supuestos!$B$8 -> 0 | E101: =-B101*Supuestos!$B$20*Supuestos!$B$18 -> 0 | F101: =0 -> 0 | G101: =F101*Supuestos!$B$9 -> 0 | H101: =-F101*Supuestos!$B$39 -> 0 | I101: =-F101*Supuestos!$B$40 -> 0 | J101: =0 -> 0 | K101: =-(Supuestos!$B$22+Supuestos!$B$41) -> -119973.66 | L101: =C101+D101+E101+G101+H101+I101+J101+K101 -> -119973.66 | M101: =L101 -> -119973.66 | N101: =L101-K101-(Supuestos!$B$41+Supuestos!$B$24) -> -3722.46 | O101: =N101 -> -3722.46
A102: 1 | B102: =Supuestos!$B$34*Supuestos!$B$46 -> 220 | C102: =B102*Supuestos!$B$7 -> 54780 | D102: =-C102*Supuestos!$B$8 -> -16434 | E102: =-B102*Supuestos!$B$20*Supuestos!$B$18 -> -1381.6 | F102: =F101*(1-Supuestos!$B$14)+B102*Supuestos!$B$13 -> 22 | G102: =F102*Supuestos!$B$9 -> 1078 | H102: =-F102*Supuestos!$B$39 -> -121.57728 | I102: =-F102*Supuestos!$B$40 -> -57.75 | J102: =-Supuestos!$B$42 -> -437.5 | K102: =0 -> 0 | L102: =C102+D102+E102+G102+H102+I102+J102+K102 -> 37425.573 | M102: =M101+L102 -> -82548.087 | N102: =L102 -> 37425.573 | O102: =O101+N102 -> 33703.113
A103: 2 | B103: =Supuestos!$B$34*Supuestos!$B$47 -> 132 | C103: =B103*Supuestos!$B$7 -> 32868 | D103: =-C103*Supuestos!$B$8 -> -9860.4 | E103: =-B103*Supuestos!$B$20*Supuestos!$B$18 -> -828.96 | F103: =F102*(1-Supuestos!$B$14)+B103*Supuestos!$B$13 -> 27.5 | G103: =F103*Supuestos!$B$9 -> 1347.5 | H103: =-F103*Supuestos!$B$39 -> -151.9716 | I103: =-F103*Supuestos!$B$40 -> -72.1875 | J103: =-Supuestos!$B$42 -> -437.5 | K103: =0 -> 0 | L103: =C103+D103+E103+G103+H103+I103+J103+K103 -> 22864.481 | M103: =M102+L103 -> -59683.606 | N103: =L103 -> 22864.481 | O103: =O102+N103 -> 56567.594
A104: 3 | B104: =Supuestos!$B$34*Supuestos!$B$48 -> 88 | C104: =B104*Supuestos!$B$7 -> 21912 | D104: =-C104*Supuestos!$B$8 -> -6573.6 | E104: =-B104*Supuestos!$B$20*Supuestos!$B$18 -> -552.64 | F104: =F103*(1-Supuestos!$B$14)+B104*Supuestos!$B$13 -> 26.675 | G104: =F104*Supuestos!$B$9 -> 1307.075 | H104: =-F104*Supuestos!$B$39 -> -147.41245 | I104: =-F104*Supuestos!$B$40 -> -70.021875 | J104: =-Supuestos!$B$42 -> -437.5 | K104: =0 -> 0 | L104: =C104+D104+E104+G104+H104+I104+J104+K104 -> 15437.901 | M104: =M103+L104 -> -44245.706 | N104: =L104 -> 15437.901 | O104: =O103+N104 -> 72005.494
A105: 4 | B105: =Supuestos!$B$34*Supuestos!$B$49 -> 66 | C105: =B105*Supuestos!$B$7 -> 16434 | D105: =-C105*Supuestos!$B$8 -> -4930.2 | E105: =-B105*Supuestos!$B$20*Supuestos!$B$18 -> -414.48 | F105: =F104*(1-Supuestos!$B$14)+B105*Supuestos!$B$13 -> 23.93875 | G105: =F105*Supuestos!$B$9 -> 1172.9987 | H105: =-F105*Supuestos!$B$39 -> -132.29128 | I105: =-F105*Supuestos!$B$40 -> -62.839219 | J105: =-Supuestos!$B$42 -> -437.5 | K105: =0 -> 0 | L105: =C105+D105+E105+G105+H105+I105+J105+K105 -> 11629.688 | M105: =M104+L105 -> -32616.017 | N105: =L105 -> 11629.688 | O105: =O104+N105 -> 83635.183
A106: 5 | B106: =Supuestos!$B$34*Supuestos!$B$50 -> 66 | C106: =B106*Supuestos!$B$7 -> 16434 | D106: =-C106*Supuestos!$B$8 -> -4930.2 | E106: =-B106*Supuestos!$B$20*Supuestos!$B$18 -> -414.48 | F106: =F105*(1-Supuestos!$B$14)+B106*Supuestos!$B$13 -> 22.160187 | G106: =F106*Supuestos!$B$9 -> 1085.8492 | H106: =-F106*Supuestos!$B$39 -> -122.46251 | I106: =-F106*Supuestos!$B$40 -> -58.170492 | J106: =-Supuestos!$B$42 -> -437.5 | K106: =0 -> 0 | L106: =C106+D106+E106+G106+H106+I106+J106+K106 -> 11557.036 | M106: =M105+L106 -> -21058.981 | N106: =L106 -> 11557.036 | O106: =O105+N106 -> 95192.219
A107: 6 | B107: =Supuestos!$B$34*Supuestos!$B$51 -> 110 | C107: =B107*Supuestos!$B$7 -> 27390 | D107: =-C107*Supuestos!$B$8 -> -8217 | E107: =-B107*Supuestos!$B$20*Supuestos!$B$18 -> -690.8 | F107: =F106*(1-Supuestos!$B$14)+B107*Supuestos!$B$13 -> 25.404122 | G107: =F107*Supuestos!$B$9 -> 1244.802 | H107: =-F107*Supuestos!$B$39 -> -140.38927 | I107: =-F107*Supuestos!$B$40 -> -66.68582 | J107: =-Supuestos!$B$42 -> -437.5 | K107: =0 -> 0 | L107: =C107+D107+E107+G107+H107+I107+J107+K107 -> 19082.427 | M107: =M106+L107 -> -1976.5544 | N107: =L107 -> 19082.427 | O107: =O106+N107 -> 114274.65
A108: 7 | B108: =Supuestos!$B$34*Supuestos!$B$52 -> 88 | C108: =B108*Supuestos!$B$7 -> 21912 | D108: =-C108*Supuestos!$B$8 -> -6573.6 | E108: =-B108*Supuestos!$B$20*Supuestos!$B$18 -> -552.64 | F108: =F107*(1-Supuestos!$B$14)+B108*Supuestos!$B$13 -> 25.312679 | G108: =F108*Supuestos!$B$9 -> 1240.3213 | H108: =-F108*Supuestos!$B$39 -> -139.88394 | I108: =-F108*Supuestos!$B$40 -> -66.445783 | J108: =-Supuestos!$B$42 -> -437.5 | K108: =0 -> 0 | L108: =C108+D108+E108+G108+H108+I108+J108+K108 -> 15382.252 | M108: =M107+L108 -> 13405.697 | N108: =L108 -> 15382.252 | O108: =O107+N108 -> 129656.9
A109: 8 | B109: =Supuestos!$B$34*Supuestos!$B$53 -> 66 | C109: =B109*Supuestos!$B$7 -> 16434 | D109: =-C109*Supuestos!$B$8 -> -4930.2 | E109: =-B109*Supuestos!$B$20*Supuestos!$B$18 -> -414.48 | F109: =F108*(1-Supuestos!$B$14)+B109*Supuestos!$B$13 -> 23.053241 | G109: =F109*Supuestos!$B$9 -> 1129.6088 | H109: =-F109*Supuestos!$B$39 -> -127.39775 | I109: =-F109*Supuestos!$B$40 -> -60.514759 | J109: =-Supuestos!$B$42 -> -437.5 | K109: =0 -> 0 | L109: =C109+D109+E109+G109+H109+I109+J109+K109 -> 11593.516 | M109: =M108+L109 -> 24999.213 | N109: =L109 -> 11593.516 | O109: =O108+N109 -> 141250.41
A110: 9 | B110: =Supuestos!$B$34*Supuestos!$B$54 -> 55 | C110: =B110*Supuestos!$B$7 -> 13695 | D110: =-C110*Supuestos!$B$8 -> -4108.5 | E110: =-B110*Supuestos!$B$20*Supuestos!$B$18 -> -345.4 | F110: =F109*(1-Supuestos!$B$14)+B110*Supuestos!$B$13 -> 20.484607 | G110: =F110*Supuestos!$B$9 -> 1003.7457 | H110: =-F110*Supuestos!$B$39 -> -113.20285 | I110: =-F110*Supuestos!$B$40 -> -53.772093 | J110: =-Supuestos!$B$42 -> -437.5 | K110: =0 -> 0 | L110: =C110+D110+E110+G110+H110+I110+J110+K110 -> 9640.3708 | M110: =M109+L110 -> 34639.584 | N110: =L110 -> 9640.3708 | O110: =O109+N110 -> 150890.78
A111: 10 | B111: =Supuestos!$B$34*Supuestos!$B$55 -> 55 | C111: =B111*Supuestos!$B$7 -> 13695 | D111: =-C111*Supuestos!$B$8 -> -4108.5 | E111: =-B111*Supuestos!$B$20*Supuestos!$B$18 -> -345.4 | F111: =F110*(1-Supuestos!$B$14)+B111*Supuestos!$B$13 -> 18.814995 | G111: =F111*Supuestos!$B$9 -> 921.93473 | H111: =-F111*Supuestos!$B$39 -> -103.97618 | I111: =-F111*Supuestos!$B$40 -> -49.389361 | J111: =-Supuestos!$B$42 -> -437.5 | K111: =0 -> 0 | L111: =C111+D111+E111+G111+H111+I111+J111+K111 -> 9572.1692 | M111: =M110+L111 -> 44211.753 | N111: =L111 -> 9572.1692 | O111: =O110+N111 -> 160462.95
...

Sheet Equilibrio
A1: Paso 3 — Punto de equilibrio del año 1
A2: Equilibrio (unidades) = costos fijos ÷ (precio − costo variable). Aquí cada copia aporta su margen del juego más el margen esperado de Pro.
A4: Concepto (MXN) | B4: MVP | C4: 3 bloques | D4: Nota
A5: Costos fijos del año 1, contando horas (desarrollo + lanzamiento + Supabase 12 m) | B5: =Supuestos!$B$21+Supuestos!$B$41+Supuestos!$B$42*12 -> 59539.06 | C5: =Supuestos!$B$22+Supuestos!$B$41+Supuestos!$B$42*12 -> 125223.66
A6: Costos fijos del año 1, solo efectivo | B6: =Supuestos!$B$41+Supuestos!$B$23+Supuestos!$B$42*12 -> 8948.26 | C6: =Supuestos!$B$41+Supuestos!$B$24+Supuestos!$B$42*12 -> 8972.46
A7: Precio del juego | B7: =Supuestos!$B$7 -> 249 | C7: =Supuestos!$B$7 -> 249
A8: Costo variable por copia (comisión + IA) | B8: =Supuestos!$B$7*Supuestos!$B$8+Supuestos!$B$19*Supuestos!$B$18 -> 75.56 | C8: =Supuestos!$B$7*Supuestos!$B$8+Supuestos!$B$20*Supuestos!$B$18 -> 80.98
A9: Margen de contribución del juego por copia | B9: =B7-B8 -> 173.44 | C9: =C7-C8 -> 168.02
A10: Margen esperado de Pro por copia | B10: =Precio!$B$18 -> 11.671074 | C10: =Precio!$B$18 -> 11.671074
A11: Margen de contribución total por copia | B11: =B9+B10 -> 185.11107 | C11: =C9+C10 -> 179.69107
A12: EQUILIBRIO contando horas (copias) | B12: =ROUNDUP(B5/B11,0) -> 322 | C12: =ROUNDUP(C5/C11,0) -> 697 | D12: Incluye las horas del equipo como costo (a $80/h).
A13: EQUILIBRIO solo efectivo (copias) | B13: =ROUNDUP(B6/B11,0) -> 49 | C13: =ROUNDUP(C6/C11,0) -> 50 | D13: El dinero que de verdad hay que recuperar.
A14: SOM anual (semana 4) | B14: =Supuestos!$B$31 -> 1100 | C14: =Supuestos!$B$31 -> 1100
A15: Equilibrio como % del SOM | B15: =B12/B14 -> 0.29272727 | C15: =C12/C14 -> 0.63363636
A16: Copias del escenario base | B16: =Supuestos!$B$33 -> 400 | C16: =Supuestos!$B$33 -> 400
A17: ¿Alcanzable con el escenario base? | B17: =IF(B16>=B12,"Sí","No: faltan "&TEXT(B12-B16,"#,##0")&" copias") -> Sí | C17: =IF(C16>=C12,"Sí","No: faltan "&TEXT(C12-C16,"#,##0")&" copias") -> No: faltan 297 copias

Sheet Taller D-F-S
A1: Bloque 5 — Las 10 partidas más caras y su clasificación D / F / S
A2: No hay BOM de hardware: las 'piezas' de un juego son sus partes de desarrollo y lanzamiento. Montos en MXN con indirectos y contingencia (alcance-niveles-costos, Desglose). D = crea el valor · F = flexible · S = establecido.
A4: # | B4: Partida | C4: MVP | D4: 3 bloques | E4: D/F/S | F4: Por qué / qué hacer si el modelo no cierra
A5: 1 | B5: Simulación de periféricos (GPIO, timers, IRQ, UART, PWM, ADC, I2C) | C5: 2392 | D5: 21528 | E5: D | F5: Sin esto no hay 'programar como en la placa real'. Se recorta alcance (menos periféricos), no calidad.
A6: 2 | B6: Motor del juego (interfaz, C++ → WASM, marco de niveles, menú) | C6: 20571.2 | D6: 20571.2 | E6: D | F6: Es el producto. Ya es lo mínimo para que el código del jugador corra.
A7: 3 | B7: Niveles del Bloque 2 · Tiempo y serie | C7: 0 | D7: 17222.4 | E7: F | F7: Se pueden lanzar después como actualización o DLC.
A8: 4 | B8: Niveles del Bloque 1 · GPIO | C8: 5740.8 | D8: 14352 | E8: D | F8: Los 5 del MVP son el núcleo; los otros 4 se pueden posponer.
A9: 5 | B9: Niveles del Bloque 3 · Analógico y buses | C9: 0 | D9: 11481.6 | E9: F | F9: Igual que el Bloque 2: posponer.
A10: 6 | B10: Arte de las máquinas nuevas de los niveles | C10: 2152.8 | D10: 9328.8 | E10: F | F10: Reutilizar sprites con cambios de color; tope de 30 h de arte (semana 6).
A11: 7 | B11: Arte y animación base (pixel art) | C11: 7774 | D11: 7774 | E11: F | F11: Es lo que hace que 'se sienta juego', pero acepta assets CC0.
A12: 8 | B12: Supabase Pro (12 meses) | C12: 5250 | D12: 5250 | E12: F | F12: Quedarse en el plan gratuito mientras no se pase de sus límites.
A13: 9 | B13: Sonido (base + por nivel) | C13: 2392 | D13: 4425.2 | E13: F | F13: Efectos CC0; música al final.
A14: 10 | B14: Copiloto IA (desarrollo) | C14: 3588 | D14: 3588 | E14: D | F14: Es el diferenciador frente a Shenzhen I/O y Turing Complete.
A15: + | B15: Comisión de Steam (30% de cada venta) | C15: =Supuestos!$B$33*Supuestos!$B$7*Supuestos!$B$8 -> 29880 | D15: =Supuestos!$B$33*Supuestos!$B$7*Supuestos!$B$8 -> 29880 | E15: S | F15: No la controlamos; la alternativa es vender también en itch.io o la página propia.
B17: La comisión de Steam (fila '+') se calcula con el escenario base y no entra en el top 10 de desarrollo.
B18: Regla del curso: si no cierra, recortar primero los F, aceptar los S; si hay que tocar un D, se replantea la propuesta de valor.
B20: Conteo
B21: D | C21: =COUNTIF(E5:E15,"D") -> 4
B22: F | C22: =COUNTIF(E5:E15,"F") -> 6
B23: S | C23: =COUNTIF(E5:E15,"S") -> 1

Sheet Ejercicios
A1: Bloque 4 — Ejercicios de matemáticas financieras (resueltos con fórmulas visibles)
A3: Ejercicio 1 — Valor futuro: US$45,000 al 7.5% anual capitalizable trimestralmente por 5 años 6 meses
A4: Periodos trimestrales (5.5 × 4) | B4: =5.5*4 -> 22
A5: VF = 45,000 × (1 + 0.075/4)^22 | B5: =45000*(1+0.075/4)^22 -> 67717.387
A6: Comprobación con FV() | B6: =FV(0.075/4,22,0,-45000) -> 67717.387
A8: Ejercicio 2 — Valor presente: $125,000 MXN en 48 meses al 12% anual compuesto mensual
A9: VP = 125,000 / (1.01)^48 | B9: =125000/(1+0.12/12)^48 -> 77532.551
A10: Comprobación con PV() | B10: =PV(0.01,48,0,-125000) -> 77532.551
A12: Ejercicio 3 — VP de flujos irregulares al 9%: año 1 $10,000; año 3 $15,000; año 5 $8,000
A13: VP | B13: =10000/1.09+15000/1.09^3+8000/1.09^5 -> 25956.515
A15: Ejercicio 4 — Inversión US$250,000; US$60,000 anuales por 6 años; tasa 11%
A16: VP de la anualidad = 60,000 × [1 − 1.11^−6] / 0.11 | B16: =60000*(1-1.11^-6)/0.11 -> 253832.27
A17: VPN = VP − 250,000 | B17: =B16-250000 -> 3832.2712
A18: TIR | B18: =IRR({-250000,60000,60000,60000,60000,60000,60000}) -> 0.11530473
A19: Decisión: VPN > 0 → se acepta, aunque por poco (TIR 11.5% apenas arriba del 11%).
A21: Ejercicio 5 — Inversión US$50,000; flujos 7,500 / 12,000 / 20,000 / 25,000; tasa 4%
A22: VPN | B22: =NPV(0.04,7500,12000,20000,25000)-50000 -> 7456.245
A23: TIR | B23: =IRR({-50000,7500,12000,20000,25000}) -> 0.091023577
A24: Decisión: VPN > 0 → se acepta.
A26: Ejercicio 6 — Inversión US$1,000,000; flujos 300K / 350K / 375K / 300K + 150K de salvamento; tasa 10%
A27: VPN | B27: =NPV(0.1,300000,350000,375000,300000+150000)-1000000 -> 151082.58
A28: TIR | B28: =IRR({-1000000,300000,350000,375000,450000}) -> 0.16351234
A29: Decisión: VPN > 0 → se acepta. Sin el salvamento el VPN bajaría en 150,000/1.1^4 ≈ $102,452.
A31: Ejercicio 7 — Proyectos X e Y, inversión $50,000, tasa 8%
A32: VPN X (25,000 × 3 años) | B32: =NPV(0.08,25000,25000,25000)-50000 -> 14427.425
A33: VPN Y (10,000 / 20,000 / 45,000) | B33: =NPV(0.08,10000,20000,45000)-50000 -> 12128.487
A34: TIR X | B34: =IRR({-50000,25000,25000,25000}) -> 0.23375193
A35: TIR Y | B35: =IRR({-50000,10000,20000,45000}) -> 0.18224831
A36: Decisión: los dos son viables; se elige X (mayor VPN y recupera el dinero antes). Y recibe casi todo al final.
A38: Ejercicio 8 — Sensibilidad del VPN del proyecto X
A39: Tasa | B39: VPN | C39: Decisión
A40: 0.08 | B40: =NPV(A40,25000,25000,25000)-50000 -> 14427.425 | C40: =IF(B40>0,"Aceptar","Rechazar") -> Aceptar
A41: 0.15 | B41: =NPV(A41,25000,25000,25000)-50000 -> 7080.6279 | C41: =IF(B41>0,"Aceptar","Rechazar") -> Aceptar
A42: 0.2 | B42: =NPV(A42,25000,25000,25000)-50000 -> 2662.037 | C42: =IF(B42>0,"Aceptar","Rechazar") -> Aceptar
A43: 0.25 | B43: =NPV(A43,25000,25000,25000)-50000 -> -1200 | C43: =IF(B43>0,"Aceptar","Rechazar") -> Rechazar
A44: El VPN cruza cero cerca del 23.4% (la TIR de X).
A46: Ejercicio 9 — TIR por interpolación: inversión US$500,000; 180K / 200K / 190K / 170K; costo de capital 14% (resuelto en clase)
A47: VPN al 14% | B47: =NPV(0.14,180000,200000,190000,170000)-500000 -> 40686.478
A48: VPN al 22% | B48: =NPV(0.22,180000,200000,190000,170000)-500000 -> -36714.382
A49: TIR interpolada = 14% + 8% × VPN14 / (VPN14 − VPN22) | B49: =0.14+0.08*B47/(B47-B48) -> 0.18205274
A50: TIR exacta con IRR() | B50: =IRR({-500000,180000,200000,190000,170000}) -> 0.17948509
A51: El curso da +40,732 y −36,560; recalculado da ≈ +40,686 y ≈ −36,714 (redondeo). La interpolación lineal sobrestima un poco la TIR (18.2% vs 17.9%) porque el VPN es curvo. La conclusión no cambia: TIR > 14% → viable.
