Workbook

Sheet Supuestos
A1: BOM preliminar — GPIO Génesis · Semana 5 · 24-sep-2026
A2: Celdas en azul = datos que se pueden cambiar. Celdas amarillas = supuestos que todavía hay que validar. Todo lo demás son fórmulas.
A4: Parámetro | B4: Valor | C4: Unidad | D4: Fuente / nota
A5: Tipo de cambio | B5: 17.5 | C5: MXN por USD | D5: FIX promedio 24-sep-2026 (17.5001), eldolar.info con dato de Banxico
A6: Claude Haiku 4.5 — entrada | B6: 1 | C6: USD por millón de tokens | D6: platform.claude.com/docs/en/about-claude/pricing (consultado 24-sep-2026)
A7: Claude Haiku 4.5 — salida | B7: 5 | C7: USD por millón de tokens | D7: Misma fuente
A8: Tokens de entrada por consulta | B8: 3000 | C8: tokens | D8: SUPUESTO: prompt de sistema ~1,500 + código ~800 + errores y traza ~700
A9: Tokens de salida por consulta | B9: 400 | C9: tokens | D9: SUPUESTO: explicación + pista en JSON
A10: Consultas a la nube por jugador (campaña completa) | B10: 300 | C10: consultas | D10: SUPUESTO: ~15 por hora × ~20 horas de juego, sin descontar las que resuelve la capa local
A11: Jugadores en el piloto (semana 13) | B11: 20 | C11: jugadores | D11: Meta de prueba con usuarios reales
A12: Precio del juego | B12: 249 | C12: MXN | D12: Punto medio del rango 199–299 MXN (semana 4)
A13: Comisión de la tienda | B13: 0.3 | C13: fracción | D13: Steam cobra 30%; en itch.io el reparto lo elige el vendedor (conservador: 30%)
A14: Regla de costo de materiales (hardware) | B14: 0.3 | C14: fracción del precio | D14: Regla del curso: costo de materiales ≤ 30% del precio de venta

Sheet Software (1a iteración)
A1: Costos de la first-iteration (solo software) y costo de la IA por jugador
A3: Concepto | B3: Proveedor | C3: Costo USD | D3: Costo MXN | E3: Cuándo se paga | F3: Fuente / nota
A4: Motor del juego | B4: Godot 4 (licencia MIT) | C4: 0 | D4: =C4*Supuestos!$B$5 -> 0 | E4: — | F4: Sin costo; sin regalías
A5: Compilador del jugador | B5: wasi-sdk / clang (Apache 2.0 + excepción LLVM) | C5: 0 | D5: =C5*Supuestos!$B$5 -> 0 | E5: — | F5: Se incluye en el instalador
A6: Runtime WebAssembly | B6: WAMR (Apache 2.0) | C6: 0 | D6: =C6*Supuestos!$B$5 -> 0 | E6: — | F6: Se enlaza al juego vía GDExtension
A7: Backend: Auth + Postgres + Edge Functions | B7: Supabase plan Free | C7: 0 | D7: =C7*Supuestos!$B$5 -> 0 | E7: Piloto | F7: Free: 500 MB de BD, 50,000 MAU, 500,000 invocaciones; el proyecto se pausa tras 1 semana sin actividad (supabase.com/pricing)
A8: Copiloto IA durante el piloto | B8: Anthropic — Claude Haiku 4.5 | C8: =Supuestos!B11*B23 -> 30 | D8: =C8*Supuestos!$B$5 -> 525 | E8: Piloto | F8: Jugadores del piloto × costo de IA por jugador (abajo). Poner límite de gasto en la consola
A9: Página de venta | B9: GitHub Pages | C9: 0 | D9: =C9*Supuestos!$B$5 -> 0 | E9: — | F9: Ya lo usamos para esta bitácora
A10: Distribución de la demo | B10: itch.io | C10: 0 | D10: =C10*Supuestos!$B$5 -> 0 | E10: Piloto | F10: Sin cuota de alta
A11: Dominio gpiogenesis.com | B11: Registrador por definir | C11: 15 | D11: =C11*Supuestos!$B$5 -> 262.5 | E11: Al lanzar | F11: ESTIMADO sin cotizar (~USD 15/año). En semana 3 el dominio estaba libre
A12: Backend en producción | B12: Supabase plan Pro | C12: 25 | D12: =C12*Supuestos!$B$5 -> 437.5 | E12: Al lanzar (mensual) | F12: USD 25/mes; evita la pausa por inactividad (supabase.com/pricing)
A13: Alta en Steam | B13: Steam Direct | C13: 100 | D13: =C13*Supuestos!$B$5 -> 1750 | E13: Al lanzar | F13: USD 100 por juego, recuperable después de USD 1,000 en ventas (partner.steamgames.com)
A14: Total para llegar al piloto (semana 13) | C14: =SUMIFS(C4:C13,E4:E13,"Piloto")+SUMIFS(C4:C13,E4:E13,"—") -> 30 | D14: =C14*Supuestos!$B$5 -> 525
A15: Total para el lanzamiento público (pagos únicos + 1 mes de backend) | C15: =SUM(C4:C13) -> 170 | D15: =C15*Supuestos!$B$5 -> 2975
A18: Costo de la IA por jugador
A20: Costo por consulta (USD) | B20: =(Supuestos!B8*Supuestos!B6+Supuestos!B9*Supuestos!B7)/1000000 -> 0.005
A21: Costo por consulta (MXN) | B21: =B20*Supuestos!B5 -> 0.0875
A23: Costo de IA por jugador, campaña completa (USD) | B23: =B20*Supuestos!B10 -> 1.5
A24: Costo de IA por jugador (MXN) | B24: =B23*Supuestos!B5 -> 26.25
A25: Ingreso neto por copia (MXN) | B25: =Supuestos!B12*(1-Supuestos!B13) -> 174.3
A26: IA como % del ingreso neto | B26: =IF(B25=0,0,B24/B25) -> 0.15060241
A27: Si la API sube 10×: IA como % del ingreso neto | B27: =B26*10 -> 1.5060241
A28: Consultas por jugador para que la IA sea ≤10% del ingreso neto (con precio actual) | B28: =IF(B20=0,0,0.1*B25/Supuestos!B5/B20) -> 199.2
A30: Nota: el costo real baja si (a) la capa local resuelve una parte de los errores, (b) se usa caché de prompt (lectura de caché de Haiku 4.5: USD 0.10 por millón) y (c) se reutilizan explicaciones de errores idénticos.

Sheet Estación (fase 2)
A1: BOM preliminar de la estación de pruebas (fase 2, fuera de la first-iteration) — precios en tiendas de México, 24-sep-2026
A3: Componente | B3: Especificación | C3: Tienda (MX) | D3: URL | E3: Precio 1 pza (MXN) | F3: Precio c/u a volumen (MXN) | G3: Cant. por estación | H3: Subtotal por estación (MXN) | I3: Disponibilidad | J3: Dato | K3: Plan B
A4: ESP32-S3 (placa de desarrollo) ★ | B4: ESP32-S3 doble USB-C, WROOM-1 | C4: UNIT Electronics | D4: https://uelectronics.com/categoria-producto/tarjetas-desarrollo/esp32/ | E4: 188 | F4: 188 | G4: 1 | H4: =F4*G4 -> 188 | I4: En catálogo ($159–188 según versión) | J4: Verificado | K4: ESP32-S3-WROOM-1-N8R8 suelto ($152) sobre PCB propia; ESP32-C6 (RISC-V) si se quiere usar el mismo clang
A5: Motorreductor N20 ★ | B5: N20 metálico 6 V, 50–500 RPM | C5: Geek Factory | D5: https://www.geekfactory.mx/producto/micro-motorreductor-n20-metalico/ | E5: 70 | F5: 68 | G5: 1 | H5: =F5*G5 -> 68 | I5: En catálogo | J5: Verificado | K5: GA12-N20 de otras tiendas
A6: Encoder para el N20 ★ (el más difícil) | B6: Óptico DFRobot SEN0116, 12 pulsos/vuelta | C6: Geek Factory | D6: https://www.geekfactory.mx/producto/encoder-para-micro-motorreductor-metalico-n20/ | E6: 195 | F6: 195 | G6: 1 | H6: =F6*G6 -> 195 | I6: En existencia. El N20 con encoder Hall integrado estaba AGOTADO en ByMechatronics y MKtronik | J6: Verificado | K6: N20 con encoder Hall por AliExpress (3–4 semanas) o disco ranurado + sensor óptico impreso en 3D
A7: Driver de motor | B7: TB6612FNG doble puente H, 1 A | C7: Geek Factory | D7: https://www.geekfactory.mx/producto/tb6612fng-puente-h-doble-controlador-de-motor/ | E7: 63 | F7: 55 | G7: 1 | H7: =F7*G7 -> 55 | I7: En existencia | J7: Verificado | K7: DRV8833
A8: IMU | B8: MPU-6050 acelerómetro + giroscopio, I²C | C8: Sandorobotics | D8: https://sandorobotics.com.mx/producto/hr0044/ | E8: 70 | F8: 63 | G8: 1 | H8: =F8*G8 -> 63 | I8: 14 pzas en existencia | J8: Verificado | K8: MPU-6050 es un chip descontinuado (hay clones); a futuro BMI160/ICM-42688
A9: Sensor de corriente | B9: INA219, I²C, 0–3.2 A | C9: UNIT Electronics | D9: https://uelectronics.com/producto/ina219-sensor-corriente-3v-5v-i2c/ | E9: 34 | F9: 34 | G9: 1 | H9: =F9*G9 -> 34 | I9: 28 pzas en existencia | J9: Verificado | K9: INA226
A10: Servomotor | B10: SG90 9 g, 0–180° | C10: UNIT Electronics | D10: https://uelectronics.com/producto/servomotor-sg90-rc-9g/ | E10: 42 | F10: 35.96 | G10: 1 | H10: =F10*G10 -> 35.96 | I10: Miles en existencia | J10: Verificado | K10: MG90S (engranes metálicos)
A11: Pantalla | B11: OLED 0.96" 128×64 I²C | C11: UNIT Electronics | D11: https://uelectronics.com/producto/display-oled-azul-y-blanco-128x64-0-96-i2c-ssd1306/ | E11: 76 | F11: 76 | G11: 1 | H11: =F11*G11 -> 76 | I11: En catálogo ($69–76 según color) | J11: Verificado | K11: LEDs de estado solamente
A12: PCB portadora de módulos | B12: 2 capas, sin PCBA; módulos con headers THT | C12: JLCPCB | D12: https://jlcpcb.com | E12: 50 | F12: 50 | G12: 1 | H12: =F12*G12 -> 50 | I12: Fabricación + envío ~1–2 semanas | J12: ESTIMADO | K12: Placa perforada en las primeras 3 unidades
A13: Base y carcasa | B13: PLA impreso en 3D, ~150 g | C13: Impresión propia | E13: 60 | F13: 60 | G13: 1 | H13: =F13*G13 -> 60 | I13: Inmediata | J13: ESTIMADO | K13: Acrílico cortado a láser
A14: Conectores, LEDs, botones, tornillería | B14: Headers, JST, 3 LEDs, 2 botones, M2/M3 | C14: Varias | E14: 80 | F14: 80 | G14: 1 | H14: =F14*G14 -> 80 | I14: Inmediata | J14: ESTIMADO | K14: —
A15: Alimentación | B15: Fuente 5 V 2 A USB-C + cable de datos | C15: Varias | E15: 60 | F15: 60 | G15: 1 | H15: =F15*G15 -> 60 | I15: Inmediata | J15: ESTIMADO | K15: Un puerto USB de PC da 500 mA: no alcanza para motor + servo
A17: Unidades de la primera tirada | H17: 10
A18: BOM por estación (volumen 10) | H18: =SUM(H4:H15) -> 964.96
A19: BOM total de la tirada | H19: =H18*H17 -> 9649.6
A20: Precio de venta mínimo por estación (BOM ÷ 30%) | H20: =H18/Supuestos!B14 -> 3216.5333
A21: Parte del BOM que es dato verificado | H21: =SUMIFS(H4:H15,J4:J15,"Verificado")/H18 -> 0.7409219
A22: ¿Cabe en el presupuesto de prototipo del curso ($3,000 MXN)? (1 estación) | H22: =IF(H18<=3000,"Sí","No") -> Sí
A24: ★ = componente crítico (se analiza en la sección 5 de la página). Precios con IVA según cada tienda; el precio a volumen usa el descuento publicado por la tienda cuando existe.
A25: Referencia de mercado (semana 2): kits básicos de Arduino $600–900 MXN; Arduino Education Starter Kit ~$8,270 MXN. El segmento individual paga 100–400 MXN por el juego.
